<?xml version="1.0"?>
<examples>
<item id="ex-20772" cql="q-9" xml="Skvorecky-Mirakl" en="" cs="cs:Skvorecky-Mirakl:0:27:4:w5" cst="asi" cssent="Napadlo mi , &#x17E;e asi p&#x159;edt&#xED;m m&#x11B;ly t&#x11B;locvik ;" use="certain" certainty="highmedium" commfuntype="decl" commfunsubtype="domn&#x11B;nka" scope="sent" pred="cs:Skvorecky-Mirakl:0:27:4:w7" tfpos="neutral" sentpos="pseudofirst" modalpersp="clear" evidence=" holky v t&#x159;et&#xED;m ro&#x10D;n&#xED;ku sed&#x11B;ly v p&#x159;il&#xE9;hav&#xFD;ch tri&#x10D;k&#xE1;ch" evidencetype="sensory" predlemma="m&#xED;t" predtag="VpFP----R-AAI--" predverbtag="VDA3PR"/>
<item id="ex-23156" cql="q-9" xml="tuckova-vyhnani_Gerty" en="" cs="cs:tuckova-vyhnani_Gerty:0:729:1:w9" cst="asi" cssent="&#x2014; J&#xE1; nev&#xED;m , zase ti voj&#xE1;ci tu asi taky nebudou v&#x11B;&#x10D;n&#x11B; ." use="confirm" certainty="highmedium" commfuntype="expr" commfunsubtype="p&#x159;esv&#x11B;d&#x10D;en&#xED;" commfunnote="nebo jistotn&#xED; a odhad?" scope="sent" pred="cs:tuckova-vyhnani_Gerty:0:729:1:w11" tfpos="neutral" sentpos="other" neg="1" modalpersp="clear" modif="taky" evidencetype="inference" comment="jako " predlemma="b&#xFD;t" predtag="VB-P---3F-NAI--" predverbtag="VDA3PF"/>
<item id="ex-24120" cql="q-9" xml="Viewegh-VychovaDivekCR" en="" cs="cs:Viewegh-VychovaDivekCR:0:1717:1:w2" cst="Asi" cssent="&quot; Asi jsem impotentn&#xED; , &quot; &#x159;ekl Oskar po chv&#xED;li ochrapt&#x11B;le ." use="certain" certainty="medium" commfuntype="decl" commfunsubtype="domn&#x11B;nka" scope="sent" pred="cs:Viewegh-VychovaDivekCR:0:1717:1:w3 cs:Viewegh-VychovaDivekCR:0:1717:1:w4" tfpos="neutral" sentpos="first" modalpersp="clear" predlemma="b&#xFD;t impotentn&#xED;" predtag="VB-S---1P-AAI-- AAMS1----1A----" predverbtag="VDA1SP ------"/>
<item id="ex-11777" cql="q-9" xml="Hrabal-Ostre_sledovane" en="" cs="cs:Hrabal-Ostre_sledovane:0:172:9:w21" cst="asi" cssent="&quot; A bejk byl potom klidnej jak ber&#xE1;nek , &quot; &#x159;ekl v kancel&#xE1;&#x159;i pomocn&#xED;k Bohou&#x161; , &quot; hehehe , u&#x17E; asi necht&#x11B;l m&#xED;t nic se sv&#x11B;tem . &quot;" use="certain" certainty="medium" commfuntype="decl" commfunsubtype="domn&#x11B;nka" scope="sent" pred="cs:Hrabal-Ostre_sledovane:0:172:9:w22 cs:Hrabal-Ostre_sledovane:0:172:9:w23" tfpos="neutral" sentpos="other" neg="1" modalpersp="clear" evidence="cs:Hrabal-Ostre_sledovane:0:172:9:w2 cs:Hrabal-Ostre_sledovane:0:172:9:w3 cs:Hrabal-Ostre_sledovane:0:172:9:w4 cs:Hrabal-Ostre_sledovane:0:172:9:w5 cs:Hrabal-Ostre_sledovane:0:172:9:w6 cs:Hrabal-Ostre_sledovane:0:172:9:w7 cs:Hrabal-Ostre_sledovane:0:172:9:w8" evidencetype="sensory" predlemma="cht&#xED;t m&#xED;t" predtag="VpMS----R-NAI-- Vf--------A-I--" predverbtag="VDA3SR VFA---"/>
<item id="ex-14216" cql="q-9" xml="Kundera-Nesnesit_lehko" en="" cs="cs:Kundera-Nesnesit_lehko:0:786:1:w10" cst="asi" cssent="Na volnou stoli&#x10D;ku u barov&#xE9;ho pultu si p&#x159;isedl chlapec asi &#x161;estn&#xE1;ctilet&#xFD; ." use="content" predlemma="" predtag="" predverbtag=""/>
<item id="ex-14195" cql="q-9" xml="Kundera-Nesmrtelnost" en="" cs="cs:Kundera-Nesmrtelnost:0:1150:2:w10" cst="asi" cssent="Pro&#x10D; u&#x17E; d&#xE1;vno nen&#xED; doma , &#x159;&#xED;kal si u&#x17E; asi po st&#xE9; a &#x161;el se pod&#xED;vat do jej&#xED;ho pokoje , i kdy&#x17E; bylo vylou&#x10D;eno , &#x17E;e by ji byl nesly&#x161;el p&#x159;ij&#xED;t dom&#x16F; ." use="content" predlemma="" predtag="" predverbtag=""/>
<item id="ex-20851" cql="q-9" xml="Skvorecky-Mirakl" en="" cs="cs:Skvorecky-Mirakl:0:1699:2:w3" cst="asi" cssent="Proto se asi od n&#x11B;j t&#x11B;&#x17E;ce d&#x11B;laj &#x10D;esk&#xFD; zdrobn&#x11B;liny ." use="certain" certainty="highmedium" commfuntype="decl" commfunsubtype="domn&#x11B;nka" commfunnote="vysv&#x11B;tlen&#xED;" scope="sent" pred="cs:Skvorecky-Mirakl:0:1699:2:w7 cs:Skvorecky-Mirakl:0:1699:2:w2" tfpos="neutral" sentpos="other" modalpersp="clear" evidence="De facto je to &#x17E;idovsk&#xFD; jm&#xE9;no" evidencetype="reasoning" predlemma="d&#x11B;lat se" predtag="VB-P---3P-AAI-6 P7--4----------" predverbtag="VDA3PP ------"/>
<item id="ex-21077" cql="q-9" xml="Skvorecky-PribehIng_1" en="" cs="cs:Skvorecky-PribehIng_1:0:2240:29:w5" cst="asi" cssent="St&#xE1;la v nich holka asi tak star&#xE1; jako j&#xE1; , dr&#x17E;ela s&#xED;&#x165;ovku a v n&#xED; m&#x11B;la &#x10D;ern&#xE9; cvi&#x10D;ky a b&#xED;l&#xE9; tri&#x10D;ko , " use="content" predlemma="" predtag="" predverbtag=""/>
<item id="ex-18173" cql="q-9" xml="panek-dejiny_ceskych" en="" cs="cs:panek-dejiny_ceskych:0:1042:2:w33" cst="asi" cssent="&#x10C;e&#x161;i se podle dohody o opci mohli do konce b&#x159;ezna 1940 odst&#x11B;hovat , ale museli by zde zanechat nemovitosti , co&#x17E; bylo pro mnoh&#xE9; z nich nep&#x159;ijateln&#xE9; , p&#x159;esto ode&#x161;lo do vnitrozem&#xED; asi 8600 osob , p&#x159;ev&#xE1;&#x17E;n&#x11B; &#x10C;ech&#x16F; ." use="content" predlemma="" predtag="" predverbtag=""/>
<item id="ex-20911" cql="q-9" xml="Skvorecky-Mirakl" en="" cs="cs:Skvorecky-Mirakl:0:3688:2:w48" cst="asi" cssent="&#x160;li jsme pr&#xE1;v&#x11B; kolem podstavce , z n&#x11B;ho&#x17E; odstranili Lenina ( p&#x159;ed n&#xED;m tam st&#xE1;l Masaryk , p&#x159;ed n&#xED;m Adolf Hitler , p&#x159;edt&#xED;m dvacet let Masaryk a p&#x16F;vodn&#x11B; Franti&#x161;ek Josef ) a m&#xED;sto n&#xED; polo&#x17E;ili &#x10D;ern&#xFD; v&#x11B;nec s inici&#xE1;lami J . P . ( le&#x17E;el tam potom asi t&#x159;i m&#x11B;s&#xED;ce , pak jej nahradila busta Lenina ) ." use="content" predlemma="" predtag="" predverbtag=""/>
<item id="ex-1651" cql="q-9" xml="ajvaz-prazdne_ulice" en="" cs="cs:ajvaz-prazdne_ulice:0:511:3:w1" cst="Asi" cssent="Asi bych nebyl zklaman&#xFD; ani son&#xE1;tou , kterou pohltily zdi ." use="certain" certainty="highmedium" commfuntype="decl" commfunsubtype="odhad" commfunnote="spekulace, re&#xE1;ln&#xFD; kondicion&#xE1;l o budoucnu" scope="sent" pred="cs:ajvaz-prazdne_ulice:0:511:3:w2 cs:ajvaz-prazdne_ulice:0:511:3:w3 cs:ajvaz-prazdne_ulice:0:511:3:w4" tfpos="neutral" sentpos="first" neg="1" modalpersp="clear" predlemma="b&#xFD;t b&#xFD;t zklaman&#xFD;" predtag="Vc-S---1----I-- VpMS----R-NAI-- AAMS1----1A----" predverbtag="A----- VCA1SP --p---"/>
<item id="ex-10595" cql="q-9" xml="hajicek-selsky_baroko" en="" cs="cs:hajicek-selsky_baroko:0:618:1:w14" cst="asi" cssent="&#x201E; &#x2026; Sl&#xE1;dk&#x16F; byli krava&#x159;i a vola&#x159;i , m&#xED;vali celkem velk&#xFD; polnosti , asi patn&#xE1;ct hektar&#x16F; ." use="content" predlemma="" predtag="" predverbtag=""/>
<item id="ex-6315" cql="q-9" xml="Douskova-Hrdy_Budzes" en="" cs="cs:Douskova-Hrdy_Budzes:0:170:9:w5" cst="asi" cssent="P&#x159;elo&#x17E;ila jsem ten obr&#xE1;zek asi nap&#x11B;tkr&#xE1;t , a&#x17E; je z n&#x11B;j &#xFA;pln&#x11B; malej &#x10D;tvere&#x10D;ek , kterej m&#xE1;m schovanej v pen&#xE1;le , v kapsi&#x10D;ce na gumy , a n&#x11B;kdy , kdy&#x17E; jsem v bezpe&#x10D;&#xED; , t&#x159;eba na z&#xE1;chod&#x11B; , tak ho vynd&#xE1;m a rozlo&#x17E;&#xED;m ." use="content" predlemma="" predtag="" predverbtag=""/>
<item id="ex-20818" cql="q-9" xml="Skvorecky-Mirakl" en="" cs="cs:Skvorecky-Mirakl:0:979:2:w2" cst="asi" cssent="Vlastn&#x11B; asi opo&#x17E;d&#x11B;n&#xE1; ob&#x11B;&#x165; svaz&#xE1;ctv&#xED; , n&#x11B;co jako Laura v mu&#x17E;sk&#xFD;m vyd&#xE1;n&#xED; ." use="certain" certainty="highmedium" commfuntype="decl" commfunsubtype="domn&#x11B;nka" scope="member" member="cs:Skvorecky-Mirakl:0:979:2:w3 cs:Skvorecky-Mirakl:0:979:2:w4 cs:Skvorecky-Mirakl:0:979:2:w5" tfpos="neutral" sentpos="other" modalpersp="clear" modif="vlastn&#x11B;" comment="elipsa" predlemma="" predtag="" predverbtag=""/>
<item id="ex-25116" cql="q-9" xml="Zmeskal-Milostny_dopis" en="" cs="cs:Zmeskal-Milostny_dopis:0:890:5:w11" cst="asi" cssent="Teprve po n&#x11B;jak&#xE9;m &#x10D;ase Maxmili&#xE1;novi do&#x161;lo , &#x17E;e to je asi ten skute&#x10D;n&#xFD; d&#x16F;vod jejich n&#xE1;v&#x161;t&#x11B;v ." use="certain" certainty="medium" commfuntype="decl" commfunsubtype="domn&#x11B;nka" scope="sent" pred="cs:Zmeskal-Milostny_dopis:0:890:5:w10 cs:Zmeskal-Milostny_dopis:0:890:5:w14" tfpos="neutral" sentpos="other" modalpersp="clear" predlemma="b&#xFD;t d&#x16F;vod" predtag="VB-S---3P-AAI-- NNIS1-----A----" predverbtag="VDA3SP ------"/>
<item id="ex-23149" cql="q-9" xml="tuckova-vyhnani_Gerty" en="" cs="cs:tuckova-vyhnani_Gerty:0:595:1:w2" cst="Asi" cssent="&#x2014; Asi pades&#xE1;tilet&#xFD; , mal&#xFD; ." use="content" predlemma="" predtag="" predverbtag=""/>
<item id="ex-22044" cql="q-9" xml="Strouhal-Zivot_Egyptan" en="" cs="cs:Strouhal-Zivot_Egyptan:0:454:1:w15" cst="asi" cssent="&#x17D;ivot prost&#xFD;ch lid&#xED; ve st&#xED;sn&#x11B;n&#xFD;ch , p&#x159;elidn&#x11B;n&#xFD;ch domech , pln&#xFD;ch hygienick&#xFD;ch z&#xE1;vad , nebyl asi p&#x159;&#xED;li&#x161; radostn&#xFD; ." dictexample="1" use="certain" certainty="highmedium" commfuntype="decl" commfunsubtype="domn&#x11B;nka" scope="sent" pred="cs:Strouhal-Zivot_Egyptan:0:454:1:w14 cs:Strouhal-Zivot_Egyptan:0:454:1:w17" tfpos="neutral" sentpos="other" neg="1" modalpersp="clear" evidencetype="inference" predlemma="b&#xFD;t radostn&#xFD;" predtag="VpIS----R-NAI-- AAIS1----1A----" predverbtag="VDA3SR ------"/>
<item id="ex-20854" cql="q-9" xml="Skvorecky-Mirakl" en="" cs="cs:Skvorecky-Mirakl:0:1775:5:w6" cst="asi" cssent="No , to mi je asi zapomn&#x11B;la d&#xE1;t ." use="certain" certainty="highmedium" commfuntype="expr" commfunsubtype="obvin&#x11B;n&#xED;" commfunnote="tot&#xE1;ln&#xED; ironie" scope="sent" pred="cs:Skvorecky-Mirakl:0:1775:5:w7" tfpos="neutral" sentpos="other" modalpersp="clear" evidencetype="inference" predlemma="zapomenout" predtag="VpFS----R-AAP-1" predverbtag="VDA3SR"/>
<item id="ex-21248" cql="q-9" xml="Skvorecky-PribehIng_2" en="" cs="cs:Skvorecky-PribehIng_2:0:2777:3:w19" cst="asi" cssent="Svobodu m&#xE1;m , a p&#x159;ipad&#xE1; mi , &#x17E;e - &#x17E;e pro m&#x11B; vlastn&#x11B; nem&#xE1; cenu - J&#xE1; - asi si mysl&#xED;&#x161; , &#x17E;e sem blbec , nebo - " use="certain" certainty="highmedium" commfuntype="expr" commfunsubtype="direktivn&#xED; p&#x159;edpoklad" commfunnote="kontaktov&#xE9;, omluvn&#xE9;, hedging" scope="sent" pred="cs:Skvorecky-PribehIng_2:0:2777:3:w20 cs:Skvorecky-PribehIng_2:0:2777:3:w21" tfpos="neutral" sentpos="other" modalpersp="clear" predlemma="se myslet" predtag="P7--3---------- VB-S---2P-AAI--" predverbtag="------ VDA2SP"/>
<item id="ex-23872" cql="q-9" xml="Vaculik-Cesky_snar" en="" cs="cs:Vaculik-Cesky_snar:0:1145:12:w20" cst="asi" cssent="- " use="content" predlemma="" predtag="" predverbtag=""/>
<item id="ex-10923" cql="q-9" xml="Havel-Dalkovy_vyslech" en="" cs="cs:Havel-Dalkovy_vyslech:0:2:32:w18" cst="asi" cssent="Nep&#x159;&#xED;slu&#x161;&#xED; mi posoudit , jak dalece jsem byl absurdn&#xED;m divadlem jako um&#x11B;leck&#xFD;m sm&#x11B;rem pou&#x10D;en &#x10D;i ovlivn&#x11B;n ( asi dost , i kdy&#x17E; je&#x161;t&#x11B; v&#x11B;t&#x161;&#xED; vliv na m&#x11B; m&#x11B;l , mysl&#xED;m , Kafka ) , nicm&#xE9;n&#x11B; rozhodn&#x11B; bych t&#x11B;&#x17E;ko n&#x11B;jak siln&#x11B;ji vn&#xED;mal absurdn&#xED; obrysy sv&#x11B;ta , kdyby ve mn&#x11B; nebyla d&#x159;&#xED;mala ta v&#xFD;choz&#xED; existenci&#xE1;ln&#xED; zku&#x161;enost , o n&#xED;&#x17E; tu mluv&#xED;m ." use="certain" certainty="highmedium" commfuntype="decl" commfunsubtype="domn&#x11B;nka" scope="member" member="cs:Havel-Dalkovy_vyslech:0:2:32:w19" tfpos="neutral" sentpos="pseudofirst" contrast="1" modalpersp="clear" predlemma="" predtag="" predverbtag=""/>
<item id="ex-1727" cql="q-9" xml="ajvaz-prazdne_ulice" en="" cs="cs:ajvaz-prazdne_ulice:0:1217:6:w8" cst="asi" cssent="M&#x11B;l sv&#x11B;tl&#xE9; vlasy a bledou ple&#x165; , asi mu pobyt na slunci ned&#x11B;lal dob&#x159;e ." use="certain" certainty="medium" commfuntype="decl" commfunsubtype="domn&#x11B;nka" scope="sent" pred="cs:ajvaz-prazdne_ulice:0:1217:6:w13" tfpos="neutral" sentpos="first" neg="1" modalpersp="clear" evidence="cs:ajvaz-prazdne_ulice:0:1217:6:w1 cs:ajvaz-prazdne_ulice:0:1217:6:w2 cs:ajvaz-prazdne_ulice:0:1217:6:w3 cs:ajvaz-prazdne_ulice:0:1217:6:w4 cs:ajvaz-prazdne_ulice:0:1217:6:w5 cs:ajvaz-prazdne_ulice:0:1217:6:w6" evidencetype="reasoning" predlemma="d&#x11B;lat" predtag="VpMS----R-NAI--" predverbtag="VDA3SR"/>
<item id="ex-22115" cql="q-9" xml="Strouhal-Zivot_Egyptan" en="" cs="cs:Strouhal-Zivot_Egyptan:0:1292:2:w4" cst="asi" cssent="Patologick&#xE1; tlou&#x161;&#x165;ka , asi lipodystrofie , postihovala puntskou kr&#xE1;lovnu , zn&#xE1;mou z reli&#xE9;fu v Hat&#x161;epsutin&#x11B; chr&#xE1;mu v D&#xE9;r el - Bahr&#xED; ." use="certain" certainty="highmedium" commfuntype="decl" commfunsubtype="domn&#x11B;nka" scope="member" tfpos="neutral" sentpos="first" modalpersp="clear" evidencetype="inference" predlemma="" predtag="" predverbtag=""/>
<item id="ex-10667" cql="q-9" xml="hakl-o_rodicich_a_dete" en="" cs="cs:hakl-o_rodicich_a_dete:0:861:1:w25" cst="asi" cssent="&#x201E; No dy&#x165; &#x159;&#xED;k&#xE1;m , le&#x17E;el jsem v posteli a vym&#x11B;&#x148;ovali jsme si zpr&#xE1;vy , ze za&#x10D;&#xE1;tku to byla jenom takov&#xE1; konverza&#x10D;ka , a asi po tejdnu to za&#x10D;alo bejt dost vosobn&#xED; . &#x201C;" use="content" predlemma="" predtag="" predverbtag=""/>
<item id="ex-23793" cql="q-9" xml="Vaculik-Cesky_snar" en="" cs="cs:Vaculik-Cesky_snar:0:730:6:w16" cst="asi" cssent="O p&#xE1;r dn&#xED; odch&#xE1;dzam ( pe&#x161;o ) na dovolenku - - do vlastnej z&#xE1;hrady , asi sa nikde nepohrnem ;" use="certain" certainty="highmedium" commfuntype="decl" commfunsubtype="domn&#x11B;nka" scope="sent" pred="cs:Vaculik-Cesky_snar:0:730:6:w17 cs:Vaculik-Cesky_snar:0:730:6:w19" tfpos="neutral" sentpos="first" neg="1" modalpersp="clear" comment="sloven&#x161;tina" predlemma="sa hrnout" predtag="X@------------- VB-P---1F-NAI-6" predverbtag="------ VDA1PF"/>
<item id="ex-18306" cql="q-9" xml="Paral-Milenci_a_vrazi" en="" cs="cs:Paral-Milenci_a_vrazi:0:243:37:w6" cst="asi" cssent="T&#x11B;sn&#x11B; p&#x159;ed smrt&#xED; bude u&#x17E; asi pomalu &#x10D;as p&#x159;estat se b&#xE1;t ." use="certain" certainty="medium" certaintynote="vy&#x161;&#x161;&#xED; st&#x159;edn&#xED;" commfuntype="direct" commfunsubtype="direktivn&#xED; introspekce" scope="sent" pred="cs:Paral-Milenci_a_vrazi:0:243:37:w4 cs:Paral-Milenci_a_vrazi:0:243:37:w8" tfpos="marked" sentpos="other" modalpersp="clear" predlemma="b&#xFD;t &#x10D;as" predtag="VB-S---3F-AAI-- NNIS1-----A----" predverbtag="VDA3SF ------"/>
<item id="ex-24035" cql="q-9" xml="viewegh-baj_letaPodPsa" en="" cs="cs:viewegh-baj_letaPodPsa:0:215:1:w3" cst="asi" cssent="&quot; Jak&#xFD; asi , &quot; odsekla babi&#x10D;ka ." use="confirm" certainty="full" commfuntype="expr" commfunnote="neum&#xED;m pojmenovat, je to tecohu jako t&#xE1;zac&#xED;, ale m&#xE1; jin&#xFD; &#xFA;&#x10D;el" scope="ellipsis" tfpos="emphasis" sentpos="last" modalpersp="clear" predlemma="" predtag="" predverbtag=""/>
<item id="ex-1800" cql="q-9" xml="Ajvaz-Zlaty_vek" en="" cs="cs:Ajvaz-Zlaty_vek:0:12:1:w5" cst="asi" cssent="Ostrov m&#xE1; v pr&#x16F;m&#x11B;ru asi dvacet kilometr&#x16F; a le&#x17E;&#xED; v Atlantick&#xE9;m oce&#xE1;nu na obratn&#xED;ku Raka mezi Kapverdsk&#xFD;mi a Kan&#xE1;rsk&#xFD;mi ostrovy ." use="content" predlemma="" predtag="" predverbtag=""/>
<item id="ex-13898" cql="q-9" xml="klima-laska_a_smeti" en="" cs="cs:klima-laska_a_smeti:0:1289:1:w2" cst="Asi" cssent="&#x201E; Asi ses v&#x10D;era moc roz&#x10D;ilil ." use="certain" certainty="highmedium" commfuntype="decl" commfunsubtype="domn&#x11B;nka" commfunnote="trochu jako vysv&#x11B;tlen&#xED;, ale nen&#xED; to tak siln&#xE1; jistota (hypot&#xE9;za, hm)" scope="sent" pred="cs:klima-laska_a_smeti:0:1289:1:w3 cs:klima-laska_a_smeti:0:1289:1:w6" tfpos="neutral" sentpos="first" modalpersp="clear" evidencetype="inference" predlemma="se|b&#xFD;t roz&#x10D;&#xED;lit" predtag="P7--4----------|VB-S---2P-AAI-1 VpMS----R-AAP--" predverbtag="------|A----- VDA2SR"/>
<item id="ex-23785" cql="q-9" xml="Vaculik-Cesky_snar" en="" cs="cs:Vaculik-Cesky_snar:0:713:3:w2" cst="Asi" cssent="&quot; Asi odjedu do Prahy , nebav&#xED; m&#x11B; n&#x11B;co d&#x11B;lat , &quot; pravil ." use="certain" certainty="medium" commfuntype="decl" commfunsubtype="introspekce" scope="sent" pred="cs:Vaculik-Cesky_snar:0:713:3:w3" tfpos="neutral" sentpos="first" modalpersp="clear" predlemma="odjet" predtag="VB-S---1P-AAP--" predverbtag="VDA1SF"/>
<item id="ex-18232" cql="q-9" xml="Paral-Milenci_a_vrazi" en="" cs="cs:Paral-Milenci_a_vrazi:0:87:231:w19" cst="asi" cssent="V odpoledn&#xED;m &#x17E;&#xE1;ru Borek post&#xE1;val p&#x159;ede dve&#x159;mi sv&#xE9;ho pokoje , zevnit&#x159; drsn&#xFD; zp&#x11B;v a n&#xE1;hle kovov&#xFD; t&#x159;esk - asi plechov&#xE1; sk&#x159;&#xED;&#x148; vr&#x17E;ena proti trubkov&#xE9;mu &#x10D;elu kavalce &#x10D;i naopak Borek proklel sv&#x11B;t od data sv&#xE9;ho zrozen&#xED; s d&#x16F;razem na tuto bolestnou ud&#xE1;lost a prchl dol&#x16F; do sklepa - v &#x161;eru na koksu zasv&#xED;tilo cosi b&#xED;l&#xE9;ho , d&#xED;v&#x10D;&#xED; nahota a Maddin krut&#xFD; pohled , Roman Gr&#xE1;f p&#x159;ed n&#xED; kle&#x10D;el a jeho d&#x11B;tsky hranat&#xE1; z&#xE1;d&#xED;&#x10D;ka se zachv&#xED;vala , tak tenhle hajzl&#xED;k dostal nakonec tuhle d&#x11B;vku , v&#x16F;bec ti ji nep&#x159;eju a je&#x161;t&#x11B; mnohem m&#xED;&#x148; tv&#x16F;j pokoj jenom pro tebe" use="certain" certainty="highmedium" commfuntype="decl" commfunsubtype="domn&#x11B;nka" scope="member" member="cs:Paral-Milenci_a_vrazi:0:87:231:w20 cs:Paral-Milenci_a_vrazi:0:87:231:w21 cs:Paral-Milenci_a_vrazi:0:87:231:w22 cs:Paral-Milenci_a_vrazi:0:87:231:w23 cs:Paral-Milenci_a_vrazi:0:87:231:w24 cs:Paral-Milenci_a_vrazi:0:87:231:w25 cs:Paral-Milenci_a_vrazi:0:87:231:w26 cs:Paral-Milenci_a_vrazi:0:87:231:w27 cs:Paral-Milenci_a_vrazi:0:87:231:w28" tfpos="neutral" sentpos="first" modalpersp="clear" evidence="cs:Paral-Milenci_a_vrazi:0:87:231:w15 cs:Paral-Milenci_a_vrazi:0:87:231:w16 cs:Paral-Milenci_a_vrazi:0:87:231:w17" evidencetype="sensory" predlemma="" predtag="" predverbtag=""/>
<item id="ex-22148" cql="q-9" xml="styblova-skalpel_pros" en="" cs="cs:styblova-skalpel_pros:0:514:5:w1" cst="Asi" cssent="Asi se tomu div&#xED;&#x161; , takhle p&#x159;&#xED;mo jsi to ode mne nesly&#x161;el ." dictexample="1" use="certain" certainty="highmedium" commfuntype="direct" commfunsubtype="direktivn&#xED; p&#x159;edpoklad" scope="sent" pred="cs:styblova-skalpel_pros:0:514:5:w4 cs:styblova-skalpel_pros:0:514:5:w2" tfpos="neutral" sentpos="first" modalpersp="clear" evidence="cs:styblova-skalpel_pros:0:514:5:w6 cs:styblova-skalpel_pros:0:514:5:w7 cs:styblova-skalpel_pros:0:514:5:w8 cs:styblova-skalpel_pros:0:514:5:w9 cs:styblova-skalpel_pros:0:514:5:w10 cs:styblova-skalpel_pros:0:514:5:w11 cs:styblova-skalpel_pros:0:514:5:w12" evidencetype="reasoning" predlemma="divit se" predtag="VB-S---2P-AAI-- P7--4----------" predverbtag="VDA2SP ------"/>
<item id="ex-15808" cql="q-9" xml="Lustig-ModlitbaProKHor" en="" cs="cs:Lustig-ModlitbaProKHor:0:474:2:w2" cst="asi" cssent="tak&#xE9; asi proto , &#x17E;e ostatn&#xED;ch devaten&#xE1;ct mu&#x17E;&#x16F; s americk&#xFD;mi pasy , i pan Herman Cohen , jako&#x17E;to dvac&#xE1;t&#xFD; , byli trochu nerv&#xF3;zn&#xED; ;" use="certain" certainty="highmedium" commfuntype="decl" commfunsubtype="domn&#x11B;nka" commfunnote="vysv&#x11B;tlen&#xED;" scope="member" member="cs:Lustig-ModlitbaProKHor:0:474:2:w3" tfpos="neutral" sentpos="pseudofirst" modalpersp="clear" modif="tak&#xE9;" predlemma="" predtag="" predverbtag=""/>
<item id="ex-23227" cql="q-9" xml="tuckova-vyhnani_Gerty" en="" cs="cs:tuckova-vyhnani_Gerty:0:2236:25:w4" cst="asi" cssent="Jak &#x159;&#xED;k&#xE1; , asi ta zatracen&#xE1; &#x10D;e&#x161;tina , co zn&#x11B;la i ze zabedn&#x11B;n&#xFD;ch vrat stodoly , z chl&#xED;v&#x16F; , kam je natla&#x10D;ili po dvac&#xED;tk&#xE1;ch , p&#x159;esn&#x11B; , aby mohli jenom st&#xE1;t , nacpan&#xED; jeden na druh&#xE9;ho ." use="certain" certainty="highmedium" commfuntype="decl" commfunsubtype="domn&#x11B;nka" scope="member" member="cs:tuckova-vyhnani_Gerty:0:2236:25:w7 cs:tuckova-vyhnani_Gerty:0:2236:25:w5 cs:tuckova-vyhnani_Gerty:0:2236:25:w6" tfpos="neutral" sentpos="first" modalpersp="clear" comment="elipsa? (nen&#xED; tam p&#x159;edchoz&#xED; kontext, ke kter&#xE9;mu by se to syntakticky nav&#xE1;zalo" predlemma="" predtag="" predverbtag=""/>
<item id="ex-2826" cql="q-9" xml="Balaban-Mozna_ze_odcha" en="" cs="cs:Balaban-Mozna_ze_odcha:0:45:3:w27" cst="asi" cssent="Pozd&#x11B;j&#x161;&#xED; zji&#x161;t&#x11B;n&#xED; , &#x17E;e vlastn&#x11B; ka&#x17E;d&#xFD; tr&#xE1;m je praskl&#xFD; , se stalo z&#xE1;kladem jeho &#x17E;ivotn&#xED;ho postoje , kter&#xFD; si po vyst&#x159;&#xED;zliv&#x11B;n&#xED; z touhy po dokonalosti formuloval asi tak , &#x17E;e kdy&#x17E; u&#x17E; mus&#xED;m b&#xFD;t praskl&#xFD; , m&#x11B;l bych b&#xFD;t aspo&#x148; praskl&#xFD; dob&#x159;e ." use="content" predlemma="" predtag="" predverbtag=""/>
<item id="ex-23169" cql="q-9" xml="tuckova-vyhnani_Gerty" en="" cs="cs:tuckova-vyhnani_Gerty:0:1315:1:w7" cst="asi" cssent="&#x2014; No j&#xE1; nev&#xED;m , v&#x161;echny asi ne ." use="certain" certainty="highmedium" commfuntype="agree" commfunsubtype="afirmace" scope="ellipsis" tfpos="neutral" sentpos="other" neg="1" contrast="1" modalpersp="clear" evidence="N&#x11B;kte&#x159;&#xED; jsou tam dote&#x10F; , t&#x159;eba zrovna B&#xFC;rgerovi taky nemuseli" evidencetype="reasoning" predlemma="" predtag="" predverbtag=""/>
<item id="ex-6338" cql="q-9" xml="Douskova-Hrdy_Budzes" en="" cs="cs:Douskova-Hrdy_Budzes:0:504:4:w3" cst="asi" cssent="P&#x159;i&#x161;lo tam asi tolik d&#x11B;t&#xED; , kolik chod&#xED; do cel&#xFD; na&#x161;&#xED; &#x161;koly , a kdy&#x17E; si n&#xE1;s ty lidi od filmu prohl&#xED;dli , &#x159;ekli , &#x17E;e m&#xE1;me s Pep&#xED;&#x10D;kem p&#x159;ij&#xED;t znova odpoledne ." use="content" predlemma="" predtag="" predverbtag=""/>
<item id="ex-25131" cql="q-9" xml="Zmeskal-Milostny_dopis" en="" cs="cs:Zmeskal-Milostny_dopis:0:1009:37:w1" cst="Asi" cssent="Asi t&#x11B; nep&#x159;ekvap&#xED; , &#x17E;e jsem si nic nekoupil ." use="certain" certainty="highmedium" commfuntype="direct" commfunsubtype="direktivn&#xED; p&#x159;edpoklad" scope="sent" pred="cs:Zmeskal-Milostny_dopis:0:1009:37:w3" tfpos="neutral" sentpos="first" neg="1" modalpersp="clear" predlemma="p&#x159;ekvapit" predtag="VB-S---3P-NAP--" predverbtag="VDA3SF"/>
<item id="ex-20760" cql="q-9" xml="skvorecky-hrichy_pater" en="" cs="cs:skvorecky-hrichy_pater:0:1391:5:w2" cst="asi" cssent="A asi mluvila peravdu : jedno voko m&#x11B;la votekl&#xFD; a jeden zub povyra&#x17E;enej , viklal se j&#xED; , ka&#x17E;d&#xE1; jsme ji musely za n&#x11B;j vz&#xED;t a zaviklat , jakej je to surovec ." use="certain" certainty="highmedium" commfuntype="decl" commfunsubtype="domn&#x11B;nka" scope="sent" pred="cs:skvorecky-hrichy_pater:0:1391:5:w3" tfpos="neutral" sentpos="pseudofirst" modalpersp="clear" evidence="cs:skvorecky-hrichy_pater:0:1391:5:w6 cs:skvorecky-hrichy_pater:0:1391:5:w7 cs:skvorecky-hrichy_pater:0:1391:5:w8 cs:skvorecky-hrichy_pater:0:1391:5:w9 cs:skvorecky-hrichy_pater:0:1391:5:w10 cs:skvorecky-hrichy_pater:0:1391:5:w11 cs:skvorecky-hrichy_pater:0:1391:5:w12 cs:skvorecky-hrichy_pater:0:1391:5:w13" evidencetype="sensory" predlemma="mluvit" predtag="VpFS----R-AAI--" predverbtag="VDA3SR"/>
<item id="ex-4732" cql="q-9" xml="Capek-Valka_s_mloky" en="" cs="cs:Capek-Valka_s_mloky:0:319:3:w5" cst="asi" cssent="A tech &#x17E;ralok&#x16F; zabili asi t&#x159;icet za ten rok , co jsem tam s nima byl ." use="content" predlemma="" predtag="" predverbtag=""/>
<item id="ex-11727" cql="q-9" xml="Hrabal-Obsluhoval_pov" en="" cs="cs:Hrabal-Obsluhoval_pov:0:20:24:w943" cst="asi" cssent="A tak jsme se vraceli z t&#xE9; slavnosti n&#x11B;kam , kde jsem je&#x161;t&#x11B; nebyl , L&#xED;za mne prosila , abych se pod&#xED;val do sv&#xE9;ho rodokmenu , &#x17E;e ur&#x10D;it&#x11B; tam mus&#xED; b&#xFD;t n&#x11B;kde n&#x11B;jak&#xFD; germ&#xE1;nsk&#xFD; p&#x159;edek , j&#xE1; jsem j&#xED; jen &#x159;ekl , &#x17E;e m&#x16F;j d&#x11B;da m&#xE1; na pomn&#xED;ku naps&#xE1;no Johan Ditie , &#x17E;e byl pansk&#xFD;m &#x161;tolbou , j&#xE1; jsem se v&#x17E;dycky za toho &#x161;tolbu od kon&#xED; styd&#x11B;l , ale L&#xED;za kdy&#x17E; tohle sly&#x161;ela , tak jsem n&#x11B;jak vyrostl v jej&#xED;ch o&#x10D;&#xED;ch , v&#xED;c ne&#x17E; kdybych byl &#x10D;esk&#xFD; hrab&#x11B; , zd&#xE1;lo se , &#x17E;e t&#xED;m Ditie spadly v&#x161;echny hradby i tenk&#xE9; st&#x11B;ny , kter&#xE9; n&#xE1;s d&#x11B;lily , celou cestu ml&#x10D;ela , pak odemkla star&#xFD; bar&#xE1;k a stoupali jsme po schodech , na ka&#x17E;d&#xE9;m pat&#x159;e mne dlouze l&#xED;bala , hladila mn&#x11B; kalhoty v rozkroku , a kdy&#x17E; jsme ve&#x161;li do jej&#xED;ho pokoj&#xED;ku , rozsv&#xED;tila stoln&#xED; lampu a byla cel&#xE1; vlhk&#xE1; , v o&#x10D;&#xED;ch i &#xFA;stech , a p&#x159;es o&#x10D;i j&#xED; padalo b&#x11B;lmo , takov&#xE1; m&#xE1;zdra , povalila mne na kanape a zase mne dlouze l&#xED;bala , jazykem mi ohmatala a spo&#x10D;&#xED;tala v&#x161;echny zuby a neust&#xE1;le na&#x159;&#xED;kala a st&#xE9;nala jako st&#xE1;le se v&#x11B;trem otev&#xED;raj&#xED;c&#xED; a zav&#xED;raj&#xED;c&#xED; nenamazan&#xE1; vr&#xE1;tka , a pak u&#x17E; se nedalo nic jin&#xE9;ho d&#x11B;lat ne&#x17E; to , na&#x10D; jsem &#x10D;ekal , co ale nevych&#xE1;zelo ode mne jako d&#x159;&#xED;v , ale vych&#xE1;zelo to z n&#xED; , on&#x11B; m&#x11B;la pot&#x159;ebu mne a dovolovala mi v&#x161;echno , zvolna se vysvl&#xE9;kla , d&#xED;vala se na to , jak se vysvl&#xE9;k&#xE1;m i j&#xE1; , myslel jsem , &#x17E;e kdy&#x17E; je na vojn&#x11B; , &#x17E;e bude m&#xED;t i n&#x11B;jakou uniformu ve form&#x11B; spodni&#x10D;ky nebo kombin&#xE9; , &#x17E;e jist&#x11B; musej&#xED; i sest&#x159;i&#x10D;ky z lazaretu m&#xED;t n&#x11B;jak&#xE9; fasovan&#xE9; pr&#xE1;dlo , ale ona m&#x11B;la v&#x161;echno tak , jak to m&#x11B;ly sle&#x10D;ny , kter&#xE9; chodily do hotelu Pa&#x159;&#xED;&#x17E; na vizitaci za p&#xE1;ny burzi&#xE1;ny , jak to m&#x11B;ly i sle&#x10D;ny od Rajsk&#xFD;ch , a potom na&#x161;e nah&#xE1; t&#x11B;la k sob&#x11B; p&#x159;ilnula , tak n&#x11B;jak bylo v&#x161;echno jakoby v tekut&#xE9;m stavu , jako bychom byli hlem&#xFD;&#x17E;di a lnuli k sob&#x11B; jen t&#xED;m vlhk&#xFD;m t&#x11B;lem vyplazen&#xFD;m z ulity , hrozn&#x11B; se ta L&#xED;za t&#x159;&#xE1;sla a chv&#x11B;la , a j&#xE1; jsem poznal poprvn&#x11B; , &#x17E;e jsem zamilovan&#xFD; a milov&#xE1;n , bylo to n&#x11B;co docela jina&#x10D;&#xED;ho ne&#x17E; d&#x159;&#xED;v , ani m&#x11B; neprosila , abych si dal pozor , nebo abych byl opatrn&#xFD; , ale v&#x161;echno bylo jen proto , aby to bylo tak , jak to bylo , pohyby a splynut&#xED; a cesta do kopce a rozsv&#x11B;tlov&#xE1;n&#xED; se a v&#xFD;st&#x159;ik sv&#x11B;tla a tlumen&#xFD;ch sup&#x11B;n&#xED; a n&#xE1;&#x159;k&#x16F; , ani pak se mne neb&#xE1;la , ani na chvilku , b&#x159;ichem se vzdouvala proti m&#xE9; tv&#xE1;&#x159;i , objala mn&#x11B; nohama hlavu mezi kl&#xED;nem tak pevn&#x11B; , a nestyd&#x11B;la se ani chvilku , ale naopak jako by to pat&#x159;ilo ke v&#x161;emu , zvedla se a nechala se jazykem t&#x159;&#xED;t a l&#xED;zat tak dlouho , a&#x17E; se vzepjala a dala mi ochutnat , a jazykem a v jazyku pro&#x17E;&#xED;t v&#x161;echno to , co se odehr&#xE1;valo v jej&#xED;m t&#x11B;le &#x2026; pak , kdy&#x17E; le&#x17E;ela na z&#xE1;dech se zalo&#x17E;en&#xFD;ma rukama a rozev&#x159;en&#xFD;ma nohama , kde pl&#xE1;l chom&#xE1;&#x10D; sv&#x11B;tl&#xFD;ch chloupk&#x16F; vy&#x10D;esan&#xFD;ch vzh&#x16F;ru do ka&#x10D;era , moje o&#x10D;i spo&#x10D;inuly na stole a tam byla kytice s jarn&#xED;mi tulip&#xE1;ny a v&#x11B;tvi&#x10D;kami z mlad&#xFD;ch b&#x159;ezov&#xFD;ch ratolest&#xED; a n&#x11B;kolik v&#x11B;tvi&#x10D;ek smr&#x10D;&#xED; , jako ve sn&#xE1;ch , ani snad ne ve vzpom&#xED;nce , ta p&#x159;i&#x161;la a&#x17E; pak , pak jsem si vzpomn&#x11B;l na n&#xE1;vratn&#xFD; motiv , utrhl jsem v&#x11B;tvi&#x10D;ky , rozd&#x11B;lal je na kousky a oblo&#x17E;il jsem jej&#xED; p&#x159;irozen&#xED; t&#x11B;mi v&#x11B;tvi&#x10D;kami , bylo to kr&#xE1;sn&#xE9; , to jej&#xED; b&#x159;icho zastlan&#xE9; kolem dokola v&#x11B;tvi&#x10D;kami ze smr&#x10D;iny , d&#xED;vala se na mne po o&#x10D;ku , a kdy&#x17E; jsem se naklonil a pol&#xED;bil ji mezi ty v&#x11B;tvi&#x10D;ky , kolem &#xFA;st jsem poc&#xED;til to pichlav&#xE9; jehli&#x10D;&#xED; , vzala mn&#x11B; n&#x11B;&#x17E;n&#x11B; hlavu do dlan&#xED; a zdvihla se a p&#x159;itiskla mi kl&#xED;n tak prudce na obli&#x10D;ej , &#x17E;e jsem za&#xFA;p&#x11B;l bolest&#xED; , a n&#x11B;kolika mocn&#xFD;mi &#x161;kubnut&#xED;mi b&#x159;icha dos&#xE1;hla takov&#xE9;ho vzru&#x161;en&#xED; , &#x17E;e pronikav&#x11B; vyk&#x159;ikla a svalila se na bok a oddychovala tak prudce , &#x17E;e jsem myslil , &#x17E;e um&#xED;r&#xE1; nebo um&#x159;e &#x2026; ale to nebylo jedno ani druh&#xE9; , jen se nade mnou naklonila a rozev&#x159;ela v&#x161;ech deset prst&#x16F; , a hrozila , &#x17E;e mi vy&#x161;kr&#xE1;be o&#x10D;i a po&#x161;kr&#xE1;be tv&#xE1;&#x159; a cel&#xE9;ho , tak byla vd&#x11B;&#x10D;n&#xE1; a spokojen&#xE1; , a znovu nade mnou rozev&#xED;rala ty nehty a v k&#x159;e&#x10D;i je zav&#xED;rala , aby se za chv&#xED;li v pl&#xE1;&#x10D;i zhroutila a tichounk&#xFD;m pl&#xE1;&#x10D;em p&#x159;e&#x161;la v drobounk&#xFD; sm&#xED;ch &#x2026; a j&#xE1; jsem byl klidn&#xFD; a tich&#xFD; , le&#x17E;el jsem zplihl&#xFD; , a vid&#x11B;l jsem , jak rychl&#xFD;mi prsty trh&#xE1; zbytky t&#x11B;ch smrkov&#xFD;ch v&#x11B;tvi&#x10D;ek , t&#x11B;ch z&#xE1;lomk&#x16F; jako d&#x11B;laj&#xED; myslivci , kdy&#x17E; zast&#x159;el&#xED; zv&#x11B;&#x159; , a vid&#x11B;l jsem , jak mi pokr&#xFD;v&#xE1; moje b&#x159;icho , moje zplihl&#xE9; pohlav&#xED; , cel&#xFD; kl&#xED;n jsem m&#x11B;l pln&#xFD; v&#x11B;tvi&#x10D;ek , a pak si mne ona nadzvedla a rukama mne hladila a l&#xED;bala ve slabin&#xE1;ch a zvolna jsem zase dost&#xE1;val erekci , a najednou se zdvihly ty v&#x11B;tvi&#x10D;ky , a z nich se prodral m&#x16F;j pyj a zvolna rostl a shazoval v&#x11B;tvi&#x10D;ky , ale L&#xED;za ty v&#x11B;tvi&#x10D;ky jazykem rovnala kolem dokola , aby pak zdvihla hlavu a zarazila si moje p&#x159;irozen&#xED; cel&#xE9; do &#xFA;st , a&#x17E; n&#x11B;kam do krku , cht&#x11B;l jsem ji odehnat , ale ona mne povalila , moje ruce odstr&#x10D;ila , d&#xED;val jsem se ke stropu a nechal jsem ji d&#x11B;lat zase j&#xE1; , co ona cht&#x11B;la d&#x11B;lat se mnou , nikdy bych se byl nenad&#xE1;l tolika rabi&#xE1;tskosti v jej&#xED;m po&#x10D;&#xED;n&#xE1;n&#xED; , skoro surov&#x11B; m&#x11B; vys&#xE1;la a&#x17E; do morku mocn&#xFD;mi &#xFA;dery a pohyby sv&#xE9; hlavy , ani&#x17E; by si odstranila v&#x11B;tvi&#x10D;ky , kter&#xE9; ji dr&#xE1;saly do krve do &#xFA;st , asi to je u Germ&#xE1;n&#x16F; zvykem &#x2026; skoro jsem se L&#xED;zy b&#xE1;l &#x2026; kdy&#x17E; se potom pl&#xED;&#x17E;ila jazykem po m&#xE9;m b&#x159;ichu , nech&#xE1;vaj&#xED;c na mn&#x11B; slinivou &#x10D;&#xE1;ru jako hlem&#xFD;&#x17E;&#x10F; , pol&#xED;bila mne a jej&#xED; &#xFA;sta byla pln&#xE1; semene a smrkov&#xE9;ho jehli&#x10D;&#xED; , a ona to nepova&#x17E;ovala za nic ne&#x10D;ist&#xE9;ho , naopak , za vrchol , za sou&#x10D;&#xE1;st m&#x161;e , toto je moje t&#x11B;lo a toto je moje krev a toto jsou moje sliny a toto jsou tvoje a moje &#x161;&#x165;&#xE1;vy , a tohleto n&#xE1;s spojilo a poj&#xED; nav&#x17E;dycky , jak mi to &#x159;ekla , proto&#x17E;e jsme si to vym&#x11B;nili navz&#xE1;jem , i s v&#x16F;n&#xED; &#x161;&#x165;&#xE1;v a chloupk&#x16F; &#x2026;" use="certain" certainty="highmedium" commfuntype="decl" commfunsubtype="domn&#x11B;nka" scope="sent" pred="cs:Hrabal-Obsluhoval_pov:0:20:24:w945 cs:Hrabal-Obsluhoval_pov:0:20:24:w948" tfpos="neutral" sentpos="first" modalpersp="clear" predlemma="b&#xFD;t zvyk" predtag="VB-S---3P-AAI-- NNIS7-----A----" predverbtag="VDA3SP ------"/>
<item id="ex-23919" cql="q-9" xml="Vaculik-Cesky_snar" en="" cs="cs:Vaculik-Cesky_snar:0:1444:10:w4" cst="asi" cssent="&#x17D;e vedouc&#xED; se asi vzep&#x159;el p&#x159;&#xED;kaz&#x16F;m a rozhodl se d&#xE1;t mi najevo , &#x17E;e d&#x11B;l&#xE1;m dob&#x159;e ." use="certain" certainty="highmedium" commfuntype="decl" commfunsubtype="domn&#x11B;nka" commfunnote="vysv&#x11B;tlen&#xED;" scope="sent" pred="cs:Vaculik-Cesky_snar:0:1444:10:w5 cs:Vaculik-Cesky_snar:0:1444:10:w3" tfpos="neutral" sentpos="other" modalpersp="clear" evidence="Dostala jsem odm&#x11B;nu , sto korun !" evidencetype="reasoning" predlemma="vzep&#x159;&#xED;t se" predtag="VpMS----R-AAP-- P7--4----------" predverbtag="VDA3SR ------"/>
<item id="ex-24215" cql="q-9" xml="Vopenka-Moje_cesta" en="" cs="cs:Vopenka-Moje_cesta:0:526:1:w8" cst="asi" cssent="Dostali jsme se k &#x10D;emusi , co asi b&#xFD;valo parkem ." use="certain" certainty="highmedium" commfuntype="decl" commfunsubtype="domn&#x11B;nka" scope="sent" pred="cs:Vopenka-Moje_cesta:0:526:1:w9 cs:Vopenka-Moje_cesta:0:526:1:w10" tfpos="neutral" sentpos="pseudofirst" modalpersp="clear" predlemma="b&#xFD;vat park" predtag="VpNS----R-AAI-- NNIS7-----A----" predverbtag="VDA3SR ------"/>
<item id="ex-23725" cql="q-9" xml="Vaculik-Cesky_snar" en="" cs="cs:Vaculik-Cesky_snar:0:502:6:w4" cst="asi" cssent="Nasb&#xED;ral jsem tam asi patn&#xE1;ct kilo zaj&#xED;mav&#xE9;ho kamen&#xED; , Madla odv&#xE1;&#x17E;ila se ur&#xFD;pnout si kol&#xE1;&#x10D; mechu s n&#x11B;kolika kuli&#x10D;kami net&#x159;esku ." use="content" predlemma="" predtag="" predverbtag=""/>
<item id="ex-21028" cql="q-9" xml="Skvorecky-PribehIng_1" en="" cs="cs:Skvorecky-PribehIng_1:0:1086:1:w1" cst="Asi" cssent="Asi u&#x17E; za&#x10D;ne biograf ." use="certain" certainty="medium" commfuntype="decl" commfunsubtype="domn&#x11B;nka" scope="sent" pred="cs:Skvorecky-PribehIng_1:0:1086:1:w3" tfpos="neutral" sentpos="first" modalpersp="clear" evidence="U dve&#x159;&#xED; n&#x11B;kdo zazvon&#xED; ." evidencetype="sensory" predlemma="za&#x10D;&#xED;t" predtag="VB-S---3P-AAP--" predverbtag="VDA3SF"/>
<item id="ex-1630" cql="q-9" xml="ajvaz-prazdne_ulice" en="" cs="cs:ajvaz-prazdne_ulice:0:355:8:w31" cst="asi" cssent="Ale pot&#xE9; , co ode mne Viola ode&#x161;la , jsem tr&#xE1;vila dlouh&#xE9; hodiny t&#xED;m , &#x17E;e jsem pozorovala prou&#x17E;ek , kter&#xFD; nebyl vy&#x161;&#x161;&#xED; ne&#x17E; milimetr , a p&#x159;em&#xFD;&#x161;lela , &#x10D;eho asi je fragmentem ." use="other" certainty="medium" commfuntype="interr" scope="sent" pred="cs:ajvaz-prazdne_ulice:0:355:8:w32 cs:ajvaz-prazdne_ulice:0:355:8:w33" tfpos="neutral" sentpos="pseudofirst" modalpersp="clear" predlemma="b&#xFD;t fragment" predtag="VB-S---3P-AAI-- NNIS7-----A----" predverbtag="VDA3SP ------"/>
<item id="ex-1847" cql="q-9" xml="Ajvaz-Zlaty_vek" en="" cs="cs:Ajvaz-Zlaty_vek:0:418:5:w21" cst="asi" cssent="Uddo jim &#x159;ekla , &#x17E;e do pal&#xE1;ce pronikli lupi&#x10D;i , zranili Tanu , kter&#xFD; je p&#x159;ekvapil , a te&#x10F; se asi skr&#xFD;vaj&#xED; v n&#x11B;kter&#xE9;m pokoji v ni&#x17E;&#x161;&#xED;m pat&#x159;e ." use="certain" certainty="highmedium" commfuntype="decl" commfunsubtype="domn&#x11B;nka" scope="sent" pred="cs:Ajvaz-Zlaty_vek:0:418:5:w22 cs:Ajvaz-Zlaty_vek:0:418:5:w20" tfpos="neutral" sentpos="other" modalpersp="clear" predlemma="skr&#xFD;vat se" predtag="VB-P---3P-AAI-- P7--4----------" predverbtag="VDA3PP ------"/>
<item id="ex-13997" cql="q-9" xml="Kohout-Hvezdna_hodina" en="" cs="cs:Kohout-Hvezdna_hodina:0:2580:4:w12" cst="asi" cssent="Otev&#x159;en&#xFD;mi ok&#xE9;nky sly&#x161;eli tup&#xE9; &#xFA;dery a kletby , p&#xE1;r jich tam asi popadalo jako ku&#x17E;elky ." dictexample="1" use="certain" certainty="highmedium" commfuntype="decl" commfunsubtype="domn&#x11B;nka" commfunnote="vysv&#x11B;tlen&#xED;" scope="sent" pred="cs:Kohout-Hvezdna_hodina:0:2580:4:w13" tfpos="neutral" sentpos="other" modalpersp="clear" evidence="cs:Kohout-Hvezdna_hodina:0:2580:4:w3 cs:Kohout-Hvezdna_hodina:0:2580:4:w4 cs:Kohout-Hvezdna_hodina:0:2580:4:w5 cs:Kohout-Hvezdna_hodina:0:2580:4:w6 cs:Kohout-Hvezdna_hodina:0:2580:4:w7" predlemma="popadat" predtag="VpNS----R-AAI--" predverbtag="VDA3SR"/>
<item id="ex-13241" cql="q-9" xml="Jirotka-Saturnin" en="" cs="cs:Jirotka-Saturnin:0:476:3:w20" cst="asi" cssent="Kdysi jsem se domn&#xED;val , &#x17E;e ty star&#xE9; zlat&#xE9; &#x10D;asy byly n&#x11B;kdy na konci minul&#xE9;ho stolet&#xED; a &#x17E;e tenkr&#xE1;t asi bylo na sv&#x11B;t&#x11B; neobvykle dob&#x159;e ." use="certain" certainty="highmedium" commfuntype="decl" commfunsubtype="domn&#x11B;nka" scope="sent" pred="cs:Jirotka-Saturnin:0:476:3:w21 cs:Jirotka-Saturnin:0:476:3:w25" tfpos="neutral" sentpos="other" modalpersp="clear" evidencetype="reasoning" predlemma="b&#xFD;t dob&#x159;e" predtag="VpNS----R-AAI-- Dg-------1A----" predverbtag="VDA3SR ------"/>
<item id="ex-13998" cql="q-9" xml="Kohout-Hvezdna_hodina" en="" cs="cs:Kohout-Hvezdna_hodina:0:2583:3:w1" cst="Asi" cssent="Asi v p&#x16F;l dvan&#xE1;ct&#xE9; vjel v&#x161;ak do dvora cyklistick&#xFD; odd&#xED;l Zbran&#xED; SS tak ti&#x161;e , &#x17E;e se mu poda&#x159;ilo obsadit p&#x159;&#xED;zem&#xED; budovy a dv&#x11B; spodn&#xED; patra , ve kter&#xFD;ch jsou i hlasatelny a technick&#xE9; provozy , odkud se vys&#xED;l&#xE1; , na&#x161;t&#x11B;st&#xED; , radoval se Sucharda , p&#x159;i&#x161;el n&#x11B;jak&#xFD; chytrol&#xED;n na to , od&#x161;roubovat v&#x10D;as v&#x161;ecky orienta&#x10D;n&#xED; n&#xE1;pisy i tabulky na dve&#x159;&#xED;ch , tak&#x17E;e tam N&#x11B;mci bloud&#xED; jak Jen&#xED;&#x10D;ek s Ma&#x159;enkou v &#x10D;ern&#xE9;m lese ." use="content" predlemma="" predtag="" predverbtag=""/>
<item id="ex-4759" cql="q-9" xml="Capek-Valka_s_mloky" en="" cs="cs:Capek-Valka_s_mloky:0:1030:2:w14" cst="asi" cssent="nebo&#x165; v tu chv&#xED;li mi po&#x10D;alo vrtat hlavou , jak&#xE9; poruchy by se asi jevily u profesora Devrienta , kdybych mu od&#x148;al prav&#xFD; &#x10D;eln&#xED; mozkov&#xFD; lalok ;" use="other" commfuntype="interr" predlemma="" predtag="" predverbtag=""/>
<item id="ex-18336" cql="q-9" xml="Paral-Milenci_a_vrazi" en="" cs="cs:Paral-Milenci_a_vrazi:0:292:1:w28" cst="asi" cssent="ITALSK&#xC1; VOJENSK&#xC1; SPR&#xC1;VA ozn&#xE1;mila Xaveriovi Strusimu , italsk&#xE9;mu voj&#xE1;kovi z prvn&#xED; sv&#x11B;tov&#xE9; v&#xE1;lky bydl&#xED;c&#xED;mu v m&#x11B;ste&#x10D;ku Massfrabei , &#x17E;e mu nebude vypl&#xE1;cen jeho d&#x16F;chod ve v&#xFD;&#x161;i na&#x161;ich asi 150 korun do t&#xE9; doby , dokud nenahrad&#xED; vojensk&#xFD; kab&#xE1;t , kter&#xFD; ztratil v prvn&#xED; sv&#x11B;tov&#xE9; v&#xE1;lce ." use="content" predlemma="" predtag="" predverbtag=""/>
<item id="ex-2842" cql="q-9" xml="Balaban-Mozna_ze_odcha" en="" cs="cs:Balaban-Mozna_ze_odcha:0:299:1:w2" cst="Asi" cssent="&quot; Asi ho zahodil do popelnice a ty ses s t&#xED;m pak sm&#xED;&#x159;il jako se v&#x161;&#xED;m , &#x17E;e jo . &quot;" use="certain" certainty="highmedium" commfuntype="decl" commfunsubtype="domn&#x11B;nka" scope="sent" pred="cs:Balaban-Mozna_ze_odcha:0:299:1:w4" tfpos="neutral" sentpos="first" modalpersp="clear" evidencetype="inference" predlemma="zahodit" predtag="VpMS----R-AAP--" predverbtag="VDA3SR"/>
<item id="ex-21091" cql="q-9" xml="Skvorecky-PribehIng_1" en="" cs="cs:Skvorecky-PribehIng_1:0:2566:4:w2" cst="asi" cssent="Jen&#x17E;e asi zlo&#x10D;in&#x16F; bandy Sl&#xE1;nsk&#xE9;ho bylo na n&#xED; moc ." use="certain" certainty="medium" commfuntype="decl" commfunsubtype="domn&#x11B;nka" scope="sent" pred="cs:Skvorecky-PribehIng_1:0:2566:4:w6 cs:Skvorecky-PribehIng_1:0:2566:4:w9" tfpos="marked" sentpos="pseudofirst" modalpersp="clear" evidencetype="inference" predlemma="b&#xFD;t moc" predtag="VpNS----R-AAI-- Db-------------" predverbtag="VDA3SR ------"/>
<item id="ex-14005" cql="q-9" xml="Kohout-Hvezdna_hodina" en="" cs="cs:Kohout-Hvezdna_hodina:0:2884:2:w6" cst="asi" cssent="&#x10C;tve&#x159;ice popelav&#xFD;ch &#x17E;en vp&#x159;edu , asi sekret&#xE1;&#x159;ek , vyvolala sp&#xED;&#x161; rozpaky , n&#x11B;meck&#xE9; zam&#x11B;stnance ozna&#x10D;en&#xE9; b&#xED;l&#xFD;mi p&#xE1;skami na ruk&#xE1;vech uv&#xED;tal u&#x17E; p&#xED;skot ." use="certain" certainty="medium" commfuntype="decl" commfunsubtype="domn&#x11B;nka" scope="member" tfpos="neutral" sentpos="other" modalpersp="clear" evidencetype="inference" comment="je apozice kontrast?" predlemma="" predtag="" predverbtag="" member="cs:Kohout-Hvezdna_hodina:0:2884:2:w7"/>
<item id="ex-23051" cql="q-9" xml="Topol-Sestra" en="" cs="cs:Topol-Sestra:0:3068:16:w3" cst="asi" cssent="Policati byli asi r&#xE1;di , &#x17E;e tu maj t&#xFD;pky pohromad&#x11B; ." use="certain" certainty="highmedium" commfuntype="decl" commfunsubtype="domn&#x11B;nka" scope="sent" pred="cs:Topol-Sestra:0:3068:16:w2 cs:Topol-Sestra:0:3068:16:w4" tfpos="neutral" sentpos="other" modalpersp="clear" evidencetype="reasoning" predlemma="b&#xFD;t r&#xE1;d" predtag="VpMP----R-AAI-- ACMP------A----" predverbtag="VDA3PR ------"/>
<item id="ex-23937" cql="q-9" xml="Vaculik-Cesky_snar" en="" cs="cs:Vaculik-Cesky_snar:0:1528:2:w3" cst="asi" cssent="Mluvili jsme asi p&#x16F;ldruh&#xE9; hodiny a pili mysliveckou z tit&#x11B;rn&#xFD;ch kovov&#xFD;ch kal&#xED;&#x161;k&#x16F; na vysok&#xE9; stopce ." use="content" predlemma="" predtag="" predverbtag=""/>
<item id="ex-20884" cql="q-9" xml="Skvorecky-Mirakl" en="" cs="cs:Skvorecky-Mirakl:0:2789:3:w4" cst="asi" cssent="Podobn&#xE9; vz&#xE1;cnosti obsahoval asi i p&#x159;eb&#xFD;vaj&#xED;c&#xED; lodn&#xED; kufr ." use="certain" certainty="highmedium" commfuntype="decl" commfunsubtype="domn&#x11B;nka" scope="member" tfpos="marked" sentpos="other" modalpersp="clear" modif="i" evidencetype="inference" predlemma="" predtag="" predverbtag=""/>
<item id="ex-23021" cql="q-9" xml="Topol-Sestra" en="" cs="cs:Topol-Sestra:0:2797:2:w4" cst="asi" cssent="Ten ruch jsem asi vid&#x11B;l jen zbytkem mystick&#xFD;ho t&#x159;et&#xED;ho oka , krz jeho z&#xE1;kal nejsp&#xED;&#x161; &#x2026; p&#xE1;r ot&#x159;&#xED;skanejch voz&#x16F; tu v kalu&#x17E;&#xED;ch st&#xE1;lo , ale jinak nikde nikdo , kolem prob&#x11B;hl pes ." use="certain" certainty="medium" commfuntype="decl" commfunsubtype="introspekce" commfunnote="korekce sebe sama" scope="sent" pred="cs:Topol-Sestra:0:2797:2:w5" tfpos="neutral" sentpos="other" modalpersp="clear" evidence="cs:Topol-Sestra:0:2797:2:w26 cs:Topol-Sestra:0:2797:2:w27 cs:Topol-Sestra:0:2797:2:w28" evidencetype="sensory" predlemma="vid&#x11B;t" predtag="VpMS----R-AAI--" predverbtag="VDA1SR"/>
<item id="ex-24314" cql="q-9" xml="Vopenka-Muj_bratr" en="" cs="cs:Vopenka-Muj_bratr:0:350:3:w8" cst="asi" cssent="Z&#xE1;rove&#x148; poc&#xED;til v&#xFD;&#x10D;itky , proto&#x17E;e Venca to asi vzal jako sv&#xE9; selh&#xE1;n&#xED; ." use="certain" certainty="medium" commfuntype="decl" commfunsubtype="domn&#x11B;nka" scope="sent" pred="cs:Vopenka-Muj_bratr:0:350:3:w9" tfpos="neutral" sentpos="other" modalpersp="clear" evidence="V uli&#x10D;ce mezi bungalovy se pak od Marka beze slova odpojil ." evidencetype="reasoning" predlemma="vz&#xED;t" predtag="VpMS----R-AAP--" predverbtag="VDA3SR"/>
<item id="ex-8800" cql="q-9" xml="Fuks-SpalovacMrtvol" en="" cs="cs:Fuks-SpalovacMrtvol:0:380:6:w20" cst="asi" cssent="Ale to by mi snad na &#x160;t&#x11B;dr&#xFD; den p&#x159;ece jen ne&#x159;&#xED;kal , " dictexample="1" use="certain" certainty="highmedium" commfuntype="decl" commfunsubtype="domn&#x11B;nka" scope="sent" pred="cs:Fuks-SpalovacMrtvol:0:380:6:w19" tfpos="neutral" sentpos="other" modalpersp="clear" modif="jen" evidence="cs:Fuks-SpalovacMrtvol:0:380:6:w2 cs:Fuks-SpalovacMrtvol:0:380:6:w3 cs:Fuks-SpalovacMrtvol:0:380:6:w4 cs:Fuks-SpalovacMrtvol:0:380:6:w5 cs:Fuks-SpalovacMrtvol:0:380:6:w6 cs:Fuks-SpalovacMrtvol:0:380:6:w7 cs:Fuks-SpalovacMrtvol:0:380:6:w8 cs:Fuks-SpalovacMrtvol:0:380:6:w9 cs:Fuks-SpalovacMrtvol:0:380:6:w10 cs:Fuks-SpalovacMrtvol:0:380:6:w11" evidencetype="reasoning" predlemma="j&#xED;t" predtag="VB-S---3P-AAI--" predverbtag="VDA3SP"/>
<item id="ex-14065" cql="q-9" xml="kohout-snezim" en="" cs="cs:kohout-snezim:0:2166:1:w2" cst="asi" cssent="Br&#xFD;le asi odlo&#x17E;ila s d&#x11B;tstv&#xED;m a z huben&#xE9; postavi&#x10D;ky vyzr&#xE1;lo t&#x159;emi porody pln&#xE9; t&#x11B;lo , po venkovsk&#xE9;m zp&#x16F;sobu povolila bohu&#x17E;el pasu , aby doplnil tajli ve v&#xE1;lec ." dictexample="1" use="certain" certainty="highmedium" commfuntype="decl" commfunsubtype="domn&#x11B;nka" scope="sent" tfpos="neutral" sentpos="other" modalpersp="clear" comment="smyslov&#xE1; inference, ale neexplicitn&#xED;" predlemma="" predtag="" predverbtag=""/>
<item id="ex-23679" cql="q-9" xml="Vaculik-Cesky_snar" en="" cs="cs:Vaculik-Cesky_snar:0:198:7:w14" cst="asi" cssent="Lubo&#x161; &#x159;ekl , &#x17E;e to je pro n&#x11B;j v&#xFD;znamn&#xE9; slovo , &#x17E;e m&#xE1;m asi pravdu , a &#x17E;e tedy svou odpov&#x11B;&#x10F; P&#x159;&#xED;bramovi zahod&#xED; ." dictexample="1" use="certain" certainty="medium" commfuntype="agree" commfunsubtype="souhlas" scope="sent" pred="cs:Vaculik-Cesky_snar:0:198:7:w13 cs:Vaculik-Cesky_snar:0:198:7:w15" tfpos="neutral" sentpos="other" modalpersp="clear" predlemma="m&#xED;t pravda" predtag="VB-S---1P-AAI-- NNFS4-----A----" predverbtag="VDA1SP ------"/>
<item id="ex-24043" cql="q-9" xml="viewegh-baj_letaPodPsa" en="" cs="cs:viewegh-baj_letaPodPsa:0:793:1:w9" cst="asi" cssent="&quot; &#x10C;eta&#x159;i Zv&#xE1;ro ! &quot; zvolal Kvid&#x16F;v otec asi o &#x10D;tvrt hodiny pozd&#x11B;ji ." use="content" predlemma="" predtag="" predverbtag=""/>
<item id="ex-13961" cql="q-9" xml="Kohout-Hvezdna_hodina" en="" cs="cs:Kohout-Hvezdna_hodina:0:190:2:w3" cst="asi" cssent="Domovn&#xED;k , asi vdovec , jak napov&#xED;daly mali&#x10D;kosti , se sna&#x17E;il d&#xE1;l o &#x10D;istotu a po&#x159;&#xE1;dek ." dictexample="1" use="certain" certainty="highmedium" commfuntype="decl" commfunsubtype="domn&#x11B;nka" scope="member" tfpos="neutral" sentpos="first" modalpersp="clear" evidence="cs:Kohout-Hvezdna_hodina:0:190:2:w6 cs:Kohout-Hvezdna_hodina:0:190:2:w7 cs:Kohout-Hvezdna_hodina:0:190:2:w8" evidencetype="reasoning" predlemma="" predtag="" predverbtag=""/>
<item id="ex-1827" cql="q-9" xml="Ajvaz-Zlaty_vek" en="" cs="cs:Ajvaz-Zlaty_vek:0:278:4:w9" cst="asi" cssent="Interpretovali nahnil&#xE9; t&#xF3;ny jako cosi , co je asi tak stejn&#xE9;ho &#x159;&#xE1;du jako chut&#x11B; zam&#x159;el&#xE9; zv&#x11B;&#x159;iny , ch&#xE1;pali p&#x159;&#xED;tomnost t&#x11B;chto t&#xF3;n&#x16F; jako rafinovanost , je&#x17E; p&#x159;in&#xE1;&#x161;&#xED; frivoln&#xED; slast z pohybu na okraji normy , slast z rizika , kter&#xE9; se rod&#xED; na hranici mezi po&#x17E;ivateln&#xFD;m a nepo&#x17E;ivateln&#xFD;m ." use="other" commfuntype="expr" commfunsubtype="p&#x159;irovn&#xE1;v&#xE1;n&#xED;, zd&#x16F;razn&#x11B;n&#xED;" comment="asi tak" predlemma="" predtag="" predverbtag=""/>
<item id="ex-25088" cql="q-9" xml="Zmeskal-Milostny_dopis" en="" cs="cs:Zmeskal-Milostny_dopis:0:660:2:w3" cst="asi" cssent="Pomoct mu asi nebudeme moct , ale medaile nikoho nic nestoj&#xED; , a kdy&#x17E; bude pat&#x159;i&#x10D;n&#xE1; spole&#x10D;ensk&#xE1; situace , tak uvid&#xED;me ." dictexample="1" use="certain" certainty="medium" commfuntype="decl" commfunsubtype="odhad do budoucnosti" scope="sent" pred="cs:Zmeskal-Milostny_dopis:0:660:2:w4 cs:Zmeskal-Milostny_dopis:0:660:2:w5 cs:Zmeskal-Milostny_dopis:0:660:2:w1" tfpos="neutral" sentpos="other" neg="1" contrast="1" modalpersp="clear" predlemma="b&#xFD;t moci pomoci" predtag="VB-P---1F-NAI-- Vf--------A-I-- Vf--------A-P--" predverbtag="A----- VDA1PF VFA---"/>
<item id="ex-20554" cql="q-9" xml="sindelka-chyba" en="" cs="cs:sindelka-chyba:0:1461:7:w3" cst="asi" cssent="Tos u&#x17E; asi zjistil s&#xE1;m ."/>
<item id="ex-23038" cql="q-9" xml="Topol-Sestra" en="" cs="cs:Topol-Sestra:0:2890:10:w1" cst="Asi" cssent="Asi aby tu b&#x11B;lostnej obvaz nepokecal , navl&#xED;k si na ruku igelitovou ta&#x161;ku ." dictexample="1" use="certain" certainty="highmedium" commfuntype="decl" commfunsubtype="domn&#x11B;nka" commfunnote="vysv&#x11B;tlen&#xED;" scope="sent" pred="cs:Topol-Sestra:0:2890:10:w6 cs:Topol-Sestra:0:2890:10:w2" tfpos="neutral" sentpos="first" neg="1" modalpersp="clear" predlemma="pokecat aby|b&#xFD;t" predtag="VpMS----R-NAP-- J,-------------|Vc----------I--" predverbtag="VCA3SP ------|A-----"/>
<item id="ex-22117" cql="q-9" xml="Strouhal-Zivot_Egyptan" en="" cs="cs:Strouhal-Zivot_Egyptan:0:1294:2:w20" cst="asi" cssent="Uk&#xE1;zalo se , &#x17E;e se i Egyp&#x165;an&#x16F;m ukl&#xE1;dal do uzlin v plicn&#xED;ch hilech uheln&#xFD; pigment ( antrak&#xF3;za ) , asi vdechov&#xE1;n&#xED;m kou&#x159;e z otev&#x159;en&#xFD;ch ohni&#x161;&#x165; ." use="certain" certainty="highmedium" commfuntype="decl" commfunsubtype="domn&#x11B;nka" commfunnote="vysv&#x11B;tlen&#xED;" scope="member" member="cs:Strouhal-Zivot_Egyptan:0:1294:2:w21" tfpos="neutral" sentpos="first" modalpersp="clear" predlemma="" predtag="" predverbtag=""/>
<item id="ex-6358" cql="q-9" xml="Douskova-Hrdy_Budzes" en="" cs="cs:Douskova-Hrdy_Budzes:0:691:3:w20" cst="asi" cssent="To nen&#xED; hrozn&#xFD; jenom proto , &#x17E;e to je hrozn&#xFD; , to je hrozn&#xFD; hlavn&#x11B; proto , &#x17E;e to asi byla ta hol&#x10D;i&#x10D;ka , co ji n&#x11B;kdy voz&#xED;me do &#x161;koly ." use="certain" certainty="highmedium" commfuntype="decl" commfunsubtype="domn&#x11B;nka" scope="sent" pred="cs:Douskova-Hrdy_Budzes:0:691:3:w21 cs:Douskova-Hrdy_Budzes:0:691:3:w23" tfpos="neutral" sentpos="other" modalpersp="clear" predlemma="b&#xFD;t hol&#x10D;i&#x10D;ka" predtag="VpFS----R-AAI-- NNFS1-----A----" predverbtag="VDA3SR ------"/>
<item id="ex-23033" cql="q-9" xml="Topol-Sestra" en="" cs="cs:Topol-Sestra:0:2882:3:w1" cst="Asi" cssent="Asi pova&#x17E;oval za nesmysln&#xFD; n&#x11B;komu pat&#x159;it ." use="certain" certainty="medium" commfuntype="decl" commfunsubtype="domn&#x11B;nka" scope="sent" pred="cs:Topol-Sestra:0:2882:3:w2" tfpos="neutral" sentpos="first" modalpersp="clear" predlemma="pova&#x17E;ovat" predtag="VpMS----R-AAI--" predverbtag="VDA3SR"/>
<item id="ex-1657" cql="q-9" xml="ajvaz-prazdne_ulice" en="" cs="cs:ajvaz-prazdne_ulice:0:567:1:w3" cst="asi" cssent="Damaskios si asi &#x159;ekl , &#x17E;e se nebude nad takov&#xFD;m jedn&#xE1;n&#xED;m roz&#x10D;ilovat a nenech&#xE1; se podlost&#xED; sv&#xE9;ho b&#xFD;val&#xE9;ho chr&#xE1;n&#x11B;nce odv&#xE1;d&#x11B;t od du&#x161;evn&#xED; pr&#xE1;ce , ale p&#x159;esto se mu v srdci usadila ho&#x159;kost a neopou&#x161;t&#x11B;la ho ani na vte&#x159;inu ." use="certain" certainty="highmedium" commfuntype="decl" commfunsubtype="domn&#x11B;nka" scope="sent" pred="cs:ajvaz-prazdne_ulice:0:567:1:w2 cs:ajvaz-prazdne_ulice:0:567:1:w4" tfpos="neutral" sentpos="other" modalpersp="clear" predlemma="se &#x159;&#xED;ci" predtag="P7--3---------- VpMS----R-AAP--" predverbtag="------ VDA3SR"/>
<item id="ex-20865" cql="q-9" xml="Skvorecky-Mirakl" en="" cs="cs:Skvorecky-Mirakl:0:2044:3:w4" cst="asi" cssent="Kolik mysl&#xED;&#x161; &#x17E;e asi ?" use="content" predlemma="" predtag="" predverbtag=""/>
<item id="ex-4730" cql="q-9" xml="Capek-Valka_s_mloky" en="" cs="cs:Capek-Valka_s_mloky:0:288:6:w10" cst="asi" cssent="A pak vylezl z vody druh&#xE9; je&#x161;t&#x11B;rka , velk&#xE9; asi jako desetilet&#xE9; kluk , a za&#x10D;al taky tak &#x165;apkat ." use="content" predlemma="" predtag="" predverbtag=""/>
</examples>
