<?xml version="1.0"?>
<examples>
  <user id="LP" email="polakova@ufal.mff.cuni.cz" name="Lucie Pol&#xE1;kov&#xE1;"/>
  <item id="ex-25713" cql="q-22" xml="Grisham-Kral_advokatu" en="" cs="cs:Grisham-Kral_advokatu:0:391:3:w2" cst="Ka&#x17E;dop&#xE1;dn&#x11B;" cssent="&quot; Ka&#x17E;dop&#xE1;dn&#x11B; je to moje budoucnost , ne va&#x161;e ." use="other" commfuntype="direct" commfunsubtype="argumentace, vymezen&#xED; se proti kom. partnerovi" commfunnote="oponov&#xE1;n&#xED;" comment="vymezov&#xE1;n&#xED; se, kontrastivn&#x11B;-konektivn&#xED; fce" predlemma="" predtag="" predverbtag="" modift=""/>
  <item id="ex-25380" cql="q-22" xml="barnes-zadny_duvod" en="" cs="cs:barnes-zadny_duvod:0:526:11:w1" cst="Ka&#x17E;dop&#xE1;dn&#x11B;" cssent="Ka&#x17E;dop&#xE1;dn&#x11B; to k hrdinstv&#xED; muselo m&#xED;t dost daleko ." use="certain" certainty="full" commfuntype="decl" commfunsubtype="shrnuj&#xED;c&#xED; p&#x159;esv&#x11B;d&#x10D;en&#xED;" scope="sent" pred="cs:barnes-zadny_duvod:0:526:11:w5 cs:barnes-zadny_duvod:0:526:11:w6" tfpos="neutral" sentpos="other" modalpersp="clear" modif="cs:barnes-zadny_duvod:0:526:11:w5" predlemma="muset m&#xED;t" predtag="VpNS----R-AAI-- Vf--------A-I--" predverbtag="VDA3SR VFA---" modift="muselo"/>
  <item id="ex-26029" cql="q-22" xml="rooney-normalni_lidi" en="" cs="cs:rooney-normalni_lidi:0:1546:8:w1" cst="Ka&#x17E;dop&#xE1;dn&#x11B;" cssent="Ka&#x17E;dop&#xE1;dn&#x11B; dne&#x161;ek je jin&#xFD; ." use="other" commfuntype="decl" commfunsubtype="p&#x159;esv&#x11B;d&#x10D;en&#xED;" commfunnote="navazov&#xE1;n&#xED;, kontrastivn&#xED; p&#x159;esv&#x11B;d&#x10D;en&#xED;" pred="cs:rooney-normalni_lidi:0:1546:8:w3 cs:rooney-normalni_lidi:0:1546:8:w4" comment="konektor" predlemma="b&#xFD;t jin&#xFD;" predtag="VB-S---3P-AAI-- AAIS1----1A----" predverbtag="VDA3SP ------" modift=""/>
  <item id="ex-26088" cql="q-22" xml="rowling-princ" en="" cs="cs:rowling-princ:0:2324:5:w1" cst="Ka&#x17E;dop&#xE1;dn&#x11B;" cssent="Ka&#x17E;dop&#xE1;dn&#x11B; , jak za okam&#x17E;ik uvid&#xED;&#x161; , Meropa odm&#xED;tla chopit se h&#x16F;lky , i kdy&#x17E; by j&#xED; to bylo zachr&#xE1;nilo &#x17E;ivot . &quot;" use="other" commfuntype="decl" predlemma="odm&#xED;tnout" predtag="VpFS----R-AAP-1" predverbtag="VDA3SR" modift="" commfunsubtype="vysv&#x11B;tlov&#xE1;n&#xED;" commfunnote="shrnut&#xED; alternativ v r&#xE1;mci vysv&#x11B;tlov&#xE1;n&#xED;" pred="cs:rowling-princ:0:2324:5:w9" comment="konektor"/>
  <item id="ex-25355" cql="q-22" xml="Banks-Most" en="" cs="cs:Banks-Most:0:1795:1:w8" cst="ka&#x17E;dop&#xE1;dn&#x11B;" cssent="&quot; Nep&#x159;ipad&#xE1; v &#xFA;vahu , to bys ka&#x17E;dop&#xE1;dn&#x11B; nat&#xE1;hl ba&#x10D;kory ." use="certain" certainty="full" commfuntype="decl" commfunsubtype="p&#x159;esv&#x11B;d&#x10D;en&#xED;" commfunnote="zd&#x16F;razn&#x11B;n&#xED; odm&#xED;tnut&#xED;" scope="sent" pred="cs:Banks-Most:0:1795:1:w9 cs:Banks-Most:0:1795:1:w10" tfpos="neutral" sentpos="other" modalpersp="clear" comment="divn&#xFD; p&#x159;eklad, podle m&#x11B; se nehod&#xED;" predlemma="nat&#xE1;hnout ba&#x10D;kora" predtag="VpMS----R-AAP-1 NNFP4-----A----" predverbtag="VCA2SP ------" modift=""/>
  <item id="ex-25988" cql="q-22" xml="Popper-hledani" en="" cs="cs:Popper-hledani:0:206:8:w1" cst="Ka&#x17E;dop&#xE1;dn&#x11B;" cssent="Ka&#x17E;dop&#xE1;dn&#x11B; tyto my&#x161;lenky pozd&#x11B;ji dost ovlivnily m&#x16F;j nov&#xFD; v&#xFD;klad Kanta a odvr&#xE1;tily m&#x16F;j z&#xE1;jem od psychologie objevu k objektivistick&#xE9; epistemologii - tj . k logice objevu ." use="other" commfuntype="decl" commfunsubtype="introspekce" pred="cs:Popper-hledani:0:206:8:w6" comment="konektor" predlemma="ovlivnit" predtag="VpFP----R-AAP--" predverbtag="VDA3PR" modift=""/>
  <item id="ex-25516" cql="q-22" xml="Burns-Mlikar" en="" cs="cs:Burns-Mlikar:0:175:59:w28" cst="ka&#x17E;dop&#xE1;dn&#x11B;" cssent="Soustavn&#x11B; jsem pletla p&#xE1;t&#xFD; p&#x159;es dev&#xE1;t&#xFD; a obracela v&#x11B;ci naruby a odsuzovala ho za v&#x11B;ci , kter&#xFD; nebyly odsouzen&#xED;hodn&#xFD; , anebo i kdyby byly , on je ka&#x17E;dop&#xE1;dn&#x11B; ned&#x11B;lal , a mysl&#xED;m , &#x17E;e on to musel pro&#x17E;&#xED;vat podobn&#x11B; , tedy vzhledem k tomu , jak se choval , i k monolog&#x16F;m , kter&#xFD;ma m&#x11B; ve sv&#xFD;m tehdej&#x161;&#xED;m du&#x161;evn&#xED;m rozpolo&#x17E;en&#xED; ob&#x161;&#x165;ast&#x148;oval ." use="certain" certainty="full" certaintynote="s negac&#xED; vy&#x161;&#x161;&#xED; m&#xED;ra" commfuntype="decl" commfunsubtype="p&#x159;esv&#x11B;d&#x10D;en&#xED;" scope="sent" pred="cs:Burns-Mlikar:0:175:59:w29" tfpos="neutral" sentpos="other" neg="1" contrast="1" modalpersp="clear" comment="u&#x17E;it&#xED; po p&#x159;&#xED;pustkov&#xE9; v&#x11B;t&#x11B;" predlemma="d&#x11B;lat" predtag="VpMS----R-NAI--" predverbtag="VDA3SR" modift=""/>
  <item id="ex-25819" cql="q-22" xml="Lessingova-Trava_zpiva" en="" cs="cs:Lessingova-Trava_zpiva:0:774:10:w2" cst="ka&#x17E;dop&#xE1;dn&#x11B;" cssent="a ka&#x17E;dop&#xE1;dn&#x11B; , kdy&#x17E; tu &#x17E;ili tak sami a tak dlouho - z toho by ka&#x17E;d&#xFD; trochu zpodiv&#xED;n&#x161;t&#x11B;l ." use="other" commfuntype="decl" commfunsubtype="vysuzov&#xE1;n&#xED;" commfunnote="argumentace, obhajoba" pred="cs:Lessingova-Trava_zpiva:0:774:10:w15 cs:Lessingova-Trava_zpiva:0:774:10:w18" comment="vyt&#x10D;en&#xE9; ze struktury, mo&#x17E;n&#xE1; anglicismus?; mo&#x17E;n&#xE1; trochu evidenci&#xE1;ln&#xED;?" predlemma="b&#xFD;t zpodiv&#xED;n&#x161;t&#x11B;t" predtag="Vc----------I-- VpMS----R-AAP--" predverbtag="A----- VCA3SP" modift=""/>
  <item id="ex-25368" cql="q-22" xml="Barnes-Arthur_a_George" en="" cs="cs:Barnes-Arthur_a_George:0:2370:5:w1" cst="Ka&#x17E;dop&#xE1;dn&#x11B;" cssent="Ka&#x17E;dop&#xE1;dn&#x11B; s nimi necht&#x11B;l j&#xED;t na policii ." dictexample="1" use="other" commfuntype="decl" commfunsubtype="shrnuj&#xED;c&#xED; vyvozen&#xED; z p&#x159;edchoz&#xED;ho" commfunnote="argumentace" pred="cs:Barnes-Arthur_a_George:0:2370:5:w4 cs:Barnes-Arthur_a_George:0:2370:5:w5" neg="1" comment="konektor" predlemma="cht&#xED;t j&#xED;t" predtag="VpMS----R-NAI-- Vf--------A-I--" predverbtag="VDA3SR VFA---" modift=""/>
  <item id="ex-25358" cql="q-22" xml="banville-more" en="" cs="cs:banville-more:0:6:15:w10" cst="ka&#x17E;dop&#xE1;dn&#x11B;" cssent="Kdo v&#xED; , co to uvnit&#x159; hledal , ale ka&#x17E;dop&#xE1;dn&#x11B; to nena&#x161;el ." use="certain" certainty="full" certaintynote="zd&#x16F;razn&#x11B;n&#xED; pln&#xE9; jistoty, je to je&#x161;t&#x11B; jistotn&#xED;?" commfuntype="decl" commfunsubtype="p&#x159;esv&#x11B;d&#x10D;en&#xED;" commfunnote="sp&#xED;&#x161; jen zd&#x16F;razn&#x11B;n&#xED;" scope="sent" pred="cs:banville-more:0:6:15:w12" tfpos="neutral" sentpos="other" neg="1" contrast="1" modalpersp="clear" modif="cs:banville-more:0:6:15:w9" comment="trochu stylisticky divn&#xE9; (p&#x159;eklad? mo&#x17E;n&#xE1;, porot&#x17E;e chyb&#xED; r&#x16F;zn&#xE9; varianty p&#x159;ed t&#xED;m), sp&#xED;&#x161; rozhodn&#x11B;" predlemma="naj&#xED;t" predtag="VpMS----R-NAP--" predverbtag="VDA3SR" modift="ale"/>
  <item id="ex-25531" cql="q-22" xml="Burns-Mlikar" en="" cs="cs:Burns-Mlikar:0:336:14:w1" cst="Ka&#x17E;dop&#xE1;dn&#x11B;" cssent="Ka&#x17E;dop&#xE1;dn&#x11B; ale m&#xE1;ti vypadla z praxe a notn&#x11B; pot&#x159;ebovala dodat odvahy ." use="other" commfuntype="decl" commfunsubtype="shrnuj&#xED;c&#xED; a navazovac&#xED;, trochu topic-shift" pred="cs:Burns-Mlikar:0:336:14:w4" comment="souv&#xFD;skyt s &quot;ale&quot;" predlemma="vypadnout" predtag="VpFS----R-AAP-1" predverbtag="VDA3SR" modift=""/>
  <item id="ex-25968" cql="q-22" xml="Nabokov-Lolita" en="" cs="cs:Nabokov-Lolita:0:807:1:w4" cst="ka&#x17E;dop&#xE1;dn&#x11B;" cssent="&quot; Ona ji ka&#x17E;dop&#xE1;dn&#x11B; m&#x11B;la ." dictexample="1" use="confirm" certainty="full" commfuntype="decl" commfunsubtype="zd&#x16F;razn&#x11B;n&#xED; a&#x17E; p&#x159;esv&#x11B;d&#x10D;ov&#xE1;n&#xED;" commfunnote="mluv&#x10D;&#xED; klade d&#x16F;raz na svou v&#xFD;pove&#x10F;, argumenta&#x10D;n&#xED;" scope="sent" pred="cs:Nabokov-Lolita:0:807:1:w5" tfpos="emphasis" sentpos="other" modalpersp="clear" comment="zd&#x16F;razn&#x11B;n&#xED; slovesa v r&#xE9;matu, nen&#xED; to navazovac&#xED; ani shrnuj&#xED;c&#xED;, sp&#xED;&#x161; argumenta&#x10D;n&#xED;" predlemma="m&#xED;t" predtag="VpFS----R-AAI--" predverbtag="VDA3SR" modift=""/>
  <item id="ex-26126" cql="q-22" xml="siddons-bezpec_vysiny" en="" cs="cs:siddons-bezpec_vysiny:0:1989:3:w1" cst="Ka&#x17E;dop&#xE1;dn&#x11B;" cssent="Ka&#x17E;dop&#xE1;dn&#x11B; sem , do t&#x11B;chto m&#xED;st ." use="other" commfuntype="decl" commfunsubtype="shrnut&#xED;" commfunnote="ale sp&#xED;&#x161; nekontrastivn&#xED;" predlemma="" predtag="" predverbtag="" modift=""/>
  <item id="ex-25269" cql="q-22" xml="adichie-amerikana" en="" cs="cs:adichie-amerikana:0:3383:3:w1" cst="Ka&#x17E;dop&#xE1;dn&#x11B;" cssent="Ka&#x17E;dop&#xE1;dn&#x11B; to necht&#x11B;la sly&#x161;et , a tak nazda&#x159;b&#x16F;h prohl&#xE1;sila :" use="other" commfuntype="decl" commfunsubtype="vyvozen&#xED;" pred="cs:adichie-amerikana:0:3383:3:w3 cs:adichie-amerikana:0:3383:3:w4" neg="1" comment="vyvozen&#xED; a zd&#x16F;razn&#x11B;n&#xED;" predlemma="cht&#xED;t sly&#x161;et" predtag="VpFS----R-NAI-- Vf--------A-I--" predverbtag="VDA3SR VFA---" modift=""/>
  <item id="ex-26184" cql="q-22" xml="Tolkien-Pan_prstenu_2" en="" cs="cs:Tolkien-Pan_prstenu_2:0:2232:3:w2" cst="ka&#x17E;dop&#xE1;dn&#x11B;" cssent="a ka&#x17E;dop&#xE1;dn&#x11B; se mu zd&#xE1;lo moud&#x159;ej&#x161;&#xED; &#x161;et&#x159;it cestovn&#xED; chl&#xE9;b elf&#x16F; na hor&#x161;&#xED; &#x10D;asy ." dictexample="1" use="certain" certainty="full" commfuntype="decl" commfunsubtype="p&#x159;esv&#x11B;d&#x10D;en&#xED;" commfunnote="zva&#x17E;ov&#xE1;n&#xED;, shrnut&#xED;, vysuzov&#xE1;n&#xED;" scope="sent" pred="cs:Tolkien-Pan_prstenu_2:0:2232:3:w5 cs:Tolkien-Pan_prstenu_2:0:2232:3:w3" tfpos="neutral" sentpos="other" modalpersp="clear" modif="cs:Tolkien-Pan_prstenu_2:0:2232:3:w5 cs:Tolkien-Pan_prstenu_2:0:2232:3:w3" predlemma="zd&#xE1;t se" predtag="VpNS----R-AAI-- P7--4----------" predverbtag="VDA3SR ------" modift="zd&#xE1;lo se"/>
  <item id="ex-26170" cql="q-22" xml="smith-sberatel" en="" cs="cs:smith-sberatel:0:1449:4:w40" cst="ka&#x17E;dop&#xE1;dn&#x11B;" cssent="&#x201E; Ned&#xE1;vno jsem p&#x159;edn&#xE1;&#x161;el n&#x11B;jak&#xFD;m &#x161;kol&#xE1;k&#x16F;m o v&#xFD;znamu Purimu &#x2013; moje p&#x159;edn&#xE1;&#x161;ka nakonec nezabrala celou hodinu , m&#x11B;l jsem probl&#xE9;my se zp&#x11B;tn&#xFD;m projektorem a objevily se i dal&#x161;&#xED; komplikace , co&#x17E; ale nen&#xED; pro tenhle p&#x159;&#xED;b&#x11B;h d&#x16F;le&#x17E;it&#xE9; - , ka&#x17E;dop&#xE1;dn&#x11B; , abych vyplnil &#x10D;as , zeptal jsem se , &#x10D;&#xED;m by cht&#x11B;li b&#xFD;t , a&#x17E; vyrostou , a &#x2013; &#x201C;" dictexample="1" use="other" commfuntype="direct" commfunsubtype="topic-shift" commfunnote="konektor" comment="navracen&#xED; se k p&#x16F;vodn&#xED;mu t&#xE9;matu po odbo&#x10D;ce, syntakticky odd&#x11B;len&#xE9;" predlemma="" predtag="" predverbtag="" modift=""/>
  <item id="ex-26154" cql="q-22" xml="smith-o_krase" en="" cs="cs:smith-o_krase:0:2606:1:w2" cst="Ka&#x17E;dop&#xE1;dn&#x11B;" cssent="&#x201E; Ka&#x17E;dop&#xE1;dn&#x11B; , j&#xE1; nechci mluvit o Carol , &#x201C; prohl&#xE1;sil Harry &#xFA;zkostliv&#x11B; ." use="other" commfuntype="agree" commfunsubtype="v&#xE1;gn&#xED; n&#xE1;vaznost v rozhovoru" pred="cs:smith-o_krase:0:2606:1:w5 cs:smith-o_krase:0:2606:1:w6" neg="1" comment="hodn&#x11B; anglicismus?" predlemma="cht&#xED;t mluvit" predtag="VB-S---1P-NAI-- Vf--------A-I--" predverbtag="VDA1SP VFA---" modift=""/>
  <item id="ex-26030" cql="q-22" xml="Roth-lidska_skvrna" en="" cs="cs:Roth-lidska_skvrna:0:84:6:w18" cst="ka&#x17E;dop&#xE1;dn&#x11B;" cssent="A na &#x10D;lov&#x11B;ka , kter&#xFD; z&#x159;ejm&#x11B; nem&#x11B;l nikdy na nic &#x161;t&#x11B;st&#xED; , si v&#x16F;bec nena&#x159;&#xED;k&#xE1; - - ka&#x17E;dop&#xE1;dn&#x11B; ne p&#x159;ede mnou ." dictexample="1" use="certain" certainty="full" certaintynote="ka&#x17E;dop&#xE1;dn&#x11B; + ne  = alespo&#x148; ne, omezen&#xED; platnosti, t&#x11B;&#x17E;ko se uchopuje m&#xED;ra jistoty" commfuntype="decl" commfunsubtype="up&#x159;esn&#x11B;n&#xED;, omezen&#xED;" scope="ellipsis" subst="cs:Roth-lidska_skvrna:0:84:6:w15 cs:Roth-lidska_skvrna:0:84:6:w13" tfpos="neutral" sentpos="first" neg="1" modalpersp="clear" predlemma="" predtag="" predverbtag="" modift=""/>
  <item id="ex-25921" cql="q-22" xml="moriarty-sedmilharky" en="" cs="cs:moriarty-sedmilharky:0:2525:5:w1" cst="Ka&#x17E;dop&#xE1;dn&#x11B;" cssent="Ka&#x17E;dop&#xE1;dn&#x11B; to zn&#xED; jako projekt , kter&#xFD; je t&#x159;eba okam&#x17E;it&#x11B; zarazit ." use="answer" commfuntype="expr" commfunsubtype="odpov&#x11B;&#x10F; s expresivitou, siln&#xFD;m p&#x159;esv&#x11B;d&#x10D;en&#xED;m" pred="cs:moriarty-sedmilharky:0:2525:5:w3" predlemma="zn&#xED;t" predtag="VB-S---3P-AAI--" predverbtag="VDA3SP" modift=""/>
  <item id="ex-25623" cql="q-22" xml="Forsyth-Ctvrty_protoko" en="" cs="cs:Forsyth-Ctvrty_protoko:0:2818:2:w3" cst="ka&#x17E;dop&#xE1;dn&#x11B;" cssent="Potom to ka&#x17E;dop&#xE1;dn&#x11B; zabal&#xED;m . &quot;" use="confirm" certainty="full" commfuntype="decl" commfunsubtype="p&#x159;esv&#x11B;d&#x10D;en&#xED;" commfunnote="samomluva, zd&#x16F;razn&#x11B;n&#xED;" scope="sent" pred="cs:Forsyth-Ctvrty_protoko:0:2818:2:w4" tfpos="neutral" sentpos="other" modalpersp="clear" comment="p&#x159;eklad? nem&#x11B;lo by b&#xFD;t opravdu?" predlemma="zabalit" predtag="VB-S---1P-AAP--" predverbtag="VDA1SF" modift=""/>
  <item id="ex-25317" cql="q-22" xml="angellova-dvoji_zivot" en="" cs="cs:angellova-dvoji_zivot:0:1303:1:w1" cst="Ka&#x17E;dop&#xE1;dn&#x11B;" cssent="Ka&#x17E;dop&#xE1;dn&#x11B; plat&#xED; , &#x17E;e &#x17E;eny obecn&#x11B; se ve fantazi&#xED;ch o sexu ve t&#x159;ech p&#x159;&#xED;li&#x161; nevy&#x17E;&#xED;vaj&#xED; ." use="other" commfuntype="decl" commfunsubtype="topic shift + p&#x159;esv&#x11B;d&#x10D;en&#xED;" commfunnote="tvrzen&#xED;, p&#x159;esv&#x11B;d&#x10D;en&#xED;" pred="cs:angellova-dvoji_zivot:0:1303:1:w2" predlemma="platit" predtag="VB-S---3P-AAI--" predverbtag="VDA3SP" modift=""/>
  <item id="ex-26039" cql="q-22" xml="rowlingova-hpot_fenix" en="" cs="cs:rowlingova-hpot_fenix:0:3030:6:w1" cst="Ka&#x17E;dop&#xE1;dn&#x11B;" cssent="Ka&#x17E;dop&#xE1;dn&#x11B; , z&#xED;tra ve dv&#x11B; m&#xE1;me tr&#xE9;nink , tak p&#x159;ij&#x10F; v&#x10D;as ." use="other" commfuntype="direct" commfunsubtype="topic shift + apel" predlemma="" predtag="" predverbtag="" modift=""/>
  <item id="ex-25675" cql="q-22" xml="Francis-Drahy_cas" en="" cs="cs:Francis-Drahy_cas:0:693:2:w1" cst="Ka&#x17E;dop&#xE1;dn&#x11B;" cssent="Ka&#x17E;dop&#xE1;dn&#x11B; jste to pachateli usnadnil . &quot;" dictexample="1" use="other" commfuntype="decl" commfunsubtype="shrnuj&#xED;c&#xED; p&#x159;esv&#x11B;d&#x10D;en&#xED;" commfunnote="konektor" pred="cs:Francis-Drahy_cas:0:693:2:w2 cs:Francis-Drahy_cas:0:693:2:w5" predlemma="b&#xFD;t usnadnit" predtag="VB-P---2P-AAI-- VpMS----R-AAP--" predverbtag="A----- VDA2vR" modift=""/>
  <item id="ex-25319" cql="q-22" xml="angellova-dvoji_zivot" en="" cs="cs:angellova-dvoji_zivot:0:1747:1:w1" cst="Ka&#x17E;dop&#xE1;dn&#x11B;" cssent="Ka&#x17E;dop&#xE1;dn&#x11B; nen&#xED; pochyb , &#x17E;e na za&#x10D;&#xE1;tku vztahu by to mohlo p&#x159;edstavovat velmi choulostiv&#xFD; probl&#xE9;m ." use="other" commfuntype="decl" commfunsubtype="p&#x159;em&#xED;t&#xE1;n&#xED;, shrnut&#xED;, introspekce" commfunnote="konektor" pred="cs:angellova-dvoji_zivot:0:1747:1:w2 cs:angellova-dvoji_zivot:0:1747:1:w3" neg="1" predlemma="b&#xFD;t pochyba" predtag="VB-S---3P-NAI-- NNFP2-----A----" predverbtag="VDA3SP ------" modift=""/>
  <item id="ex-25594" cql="q-22" xml="evans-pomezi" en="" cs="cs:evans-pomezi:0:3001:10:w1" cst="Ka&#x17E;dop&#xE1;dn&#x11B;" cssent="Ka&#x17E;dop&#xE1;dn&#x11B; se na&#x161;tvala a posledn&#xED; pr&#xE1;zdninov&#xFD; t&#xFD;den spolu tak&#x159;ka nepromluvili ." use="other" commfuntype="decl" commfunsubtype="vy&#xFA;st&#x11B;n&#xED; d&#x11B;je" commfunnote="konektor" pred="cs:evans-pomezi:0:3001:10:w3 cs:evans-pomezi:0:3001:10:w2" predlemma="na&#x161;tvat se" predtag="VpFS----R-AAP-- P7--4----------" predverbtag="VDA3SR ------" modift=""/>
  <item id="ex-25887" cql="q-22" xml="lowry-hledani_modre" en="" cs="cs:lowry-hledani_modre:0:309:1:w2" cst="Ka&#x17E;dop&#xE1;dn&#x11B;" cssent="&#x201E; Ka&#x17E;dop&#xE1;dn&#x11B; Rada Str&#xE1;&#x17E;c&#x16F; ten p&#x159;&#xED;pad p&#x159;ezkoumala a prohl&#xE1;sila , &#x17E;e Vandara to neud&#x11B;lala , &#x201C; &#x159;ekla Kira ." use="other" commfuntype="decl" commfunsubtype="vyvozen&#xED;" commfunnote="konektor" pred="cs:lowry-hledani_modre:0:309:1:w7" predlemma="p&#x159;ezkoumat" predtag="VpFS----R-AAP--" predverbtag="VDA3SR" modift=""/>
  <item id="ex-25372" cql="q-22" xml="Barnes-Arthur_a_George" en="" cs="cs:Barnes-Arthur_a_George:0:3013:6:w1" cst="Ka&#x17E;dop&#xE1;dn&#x11B;" cssent="Ka&#x17E;dop&#xE1;dn&#x11B; te&#x10F; s pevn&#x11B; up&#x159;en&#xFD;m pohledem na popeln&#xED;k zam&#xE1;&#x10D;kl zbytek slu&#x161;n&#xE9;ho doutn&#xED;ku , kter&#xFD; se jist&#x11B; dal je&#x161;t&#x11B; dokou&#x159;it ." use="other" commfuntype="decl" commfunsubtype="m&#xED;rn&#xFD; topic-shift" commfunnote="nen&#xED; to shrnut&#xED; ani vysuzov&#xE1;n&#xED;, sp&#xED;&#x161; lehk&#xFD; posun k jin&#xE9;mu, &#x10D;i d&#x11B;j na pozad&#xED; &#xFA;vah" pred="cs:Barnes-Arthur_a_George:0:3013:6:w9" comment="d&#x11B;j na pozad&#xED; &#xFA;vah, jak&#xFD;si background?" predlemma="zam&#xE1;&#x10D;knout" predtag="VpMS----R-AAP-1" predverbtag="VDA3SR" modift=""/>
  <item id="ex-25545" cql="q-22" xml="Christie-VrazdaVOrient" en="" cs="cs:Christie-VrazdaVOrient:0:2552:2:w5" cst="ka&#x17E;dop&#xE1;dn&#x11B;" cssent="Ale p&#x159;&#xED;&#x161;t&#xED; ot&#xE1;zka n&#xE1;m ka&#x17E;dop&#xE1;dn&#x11B; d&#xE1;v&#xE1; jak&#xE9;si mo&#x17E;nosti ." use="certain" certainty="full" certaintynote="na hran&#x11B; s jin&#xFD;m u&#x17E;it&#xED;m, z&#xE1;le&#x17E;&#xED; na origin&#xE1;le" commfuntype="decl" commfunsubtype="zd&#x16F;raz&#x148;ovac&#xED;" commfunnote="povzbuzen&#xED; po ne&#xFA;sp&#x11B;chu" scope="sent" pred="cs:Christie-VrazdaVOrient:0:2552:2:w6" tfpos="neutral" sentpos="other" contrast="1" modalpersp="clear" modif="cs:Christie-VrazdaVOrient:0:2552:2:w1" comment="zes&#xED;len&#xED; konektoru &quot;ale&quot;" predlemma="d&#xE1;vat" predtag="VB-S---3P-AAI--" predverbtag="VDA3SP" modift="Ale"/>
  <item id="ex-26128" cql="q-22" xml="silva-tajna_sluzba" en="" cs="cs:silva-tajna_sluzba:0:653:4:w1" cst="Ka&#x17E;dop&#xE1;dn&#x11B;" cssent="Ka&#x17E;dop&#xE1;dn&#x11B; , a&#x165; se to dostalo ven jakkoliv , nem&#x16F;&#x17E;ete opustit zemi , dokud se va&#x161;e &#xFA;&#x10D;ast na tomto incidentu &#x159;&#xE1;dn&#x11B; nevysv&#x11B;tl&#xED; a neprojedn&#xE1; v p&#x159;&#xED;slu&#x161;n&#xE9;m f&#xF3;ru . &#x201C;" use="other" commfuntype="direct" commfunsubtype="vyvozen&#xED;, z&#xE1;kaz" commfunnote="konektor" neg="1" comment="v&#xFD;&#x10D;et variant netradi&#x10D;n&#x11B; a&#x17E; PO v&#xFD;razu ka&#x17E;dop&#xE1;dn&#x11B; (ve vsuvce)" predlemma="" predtag="" predverbtag="" modift=""/>
  <item id="ex-25995" cql="q-22" xml="Popper-Otevrena_spol_2" en="" cs="cs:Popper-Otevrena_spol_2:0:456:6:w11" cst="ka&#x17E;dop&#xE1;dn&#x11B;" cssent="Vypad&#xE1; to tak , jakoby byl podv&#xE1;d&#x11B;n nebo okr&#xE1;d&#xE1;n , ka&#x17E;dop&#xE1;dn&#x11B; , jako by nedostal zaplaceno podle v&#x161;eobecn&#xE9;ho z&#xE1;kona , p&#x159;edpokl&#xE1;dan&#xE9;ho teori&#xED; hodnoty , toti&#x17E; z&#xE1;kona , &#x17E;e v&#x161;echny zaplacen&#xE9; faktick&#xE9; ceny jsou alespo&#x148; p&#x159;ibli&#x17E;n&#x11B; ur&#x10D;eny hodnotou zbo&#x17E;&#xED; ." use="certain" certainty="full" certaintynote="jistotn&#xED; kv&#x16F;li domn&#x11B;nce, kondicion&#xE1;lu a slovesu &quot;vypadat&quot;" commfuntype="decl" commfunsubtype="vyvozov&#xE1;n&#xED;, p&#x159;esv&#x11B;d&#x10D;en&#xED;" commfunnote="shrnut&#xED; p&#x159;edchoz&#xED;ho pod jeden n&#xE1;zev (nikoli vylou&#x10D;en&#xED; p&#x159;edchoz&#xED;ho)" scope="sent" pred="cs:Popper-Otevrena_spol_2:0:456:6:w15 cs:Popper-Otevrena_spol_2:0:456:6:w14" tfpos="marked" sentpos="other" neg="1" modalpersp="clear" comment="synt. osamostatn&#x11B;n&#xE9;" predlemma="dostat b&#xFD;t" predtag="VpMS----R-NAP-- Vc----------I--" predverbtag="VCA3SP A-----" modift=""/>
  <item id="ex-26102" cql="q-22" xml="Rushdie-MauruvPosl_Vzd" en="" cs="cs:Rushdie-MauruvPosl_Vzd:0:705:1:w3" cst="ka&#x17E;dop&#xE1;dn&#x11B;" cssent="Ina si ka&#x17E;dop&#xE1;dn&#x11B; ucpala u&#x161;i p&#x159;ed matkou a sout&#x11B;&#x17E;ila s n&#xED; jedin&#xFD;m zp&#x16F;sobem , o n&#x11B;m&#x17E; si myslela , &#x17E;e j&#xED; je dop&#x159;&#xE1;n : svou kr&#xE1;sou ." use="other" commfuntype="decl" commfunsubtype="topic-shift, uveden&#xED; kontrastu" commfunnote="konektor, vysok&#xE1; v&#xFD;stavba (uvozuje nov&#xFD; odstavec)" pred="cs:Rushdie-MauruvPosl_Vzd:0:705:1:w4 cs:Rushdie-MauruvPosl_Vzd:0:705:1:w2" predlemma="ucpat se" predtag="VpFS----R-AAP-- P7--3----------" predverbtag="VDA3SR ------" modift=""/>
  <item id="ex-25353" cql="q-22" xml="Banks-Most" en="" cs="cs:Banks-Most:0:1756:5:w9" cst="ka&#x17E;dop&#xE1;dn&#x11B;" cssent="V tom okam&#x17E;iku poc&#xED;til podivnou sm&#x11B;sici emoc&#xED; , ka&#x17E;dop&#xE1;dn&#x11B; l&#xE1;sku , ale sou&#x10D;asn&#x11B; i z&#xE1;vistiv&#xFD; obdiv ." use="certain" certainty="full" certaintynote="v&#xED;ce ne&#x17E; 100%" commfuntype="decl" commfunsubtype="p&#x159;esv&#x11B;d&#x10D;en&#xED;" scope="member" member="cs:Banks-Most:0:1756:5:w10" tfpos="neutral" sentpos="other" contrast="1" modalpersp="clear" modif="cs:Banks-Most:0:1756:5:w12 cs:Banks-Most:0:1756:5:w13 cs:Banks-Most:0:1756:5:w14" comment="trochu konektivn&#xED; fce, stup&#x148;ov&#xE1;n&#xED;" predlemma="" predtag="" predverbtag="" modift="ale sou&#x10D;asn&#x11B; i"/>
  <item id="ex-25305" cql="q-22" xml="Amis-Stastny_Jim" en="" cs="cs:Amis-Stastny_Jim:0:1422:7:w3" cst="ka&#x17E;dop&#xE1;dn&#x11B;" cssent="Michal byl ka&#x17E;dop&#xE1;dn&#x11B; v nejbli&#x17E;&#x161;&#xED;ch dnech o&#x10D;ek&#xE1;v&#xE1;n doma , kde ho m&#x11B;la anglick&#xE1; kuchyn&#x11B; a mate&#x159;sk&#xE1; p&#xE9;&#x10D;e p&#x159;iv&#xE9;st do po&#x159;&#xE1;dku ." use="other" commfuntype="decl" commfunsubtype="navazovac&#xED;, kontrastivn&#xED;" commfunnote="konektor" pred="cs:Amis-Stastny_Jim:0:1422:7:w2 cs:Amis-Stastny_Jim:0:1422:7:w7" predlemma="b&#xFD;t o&#x10D;ek&#xE1;vat" predtag="VpMS----R-AAI-- VsMS------API--" predverbtag="A----- VDP3SR" modift=""/>
  <item id="ex-26026" cql="q-22" xml="rooney-normalni_lidi" en="" cs="cs:rooney-normalni_lidi:0:364:4:w1" cst="Ka&#x17E;dop&#xE1;dn&#x11B;" cssent="Ka&#x17E;dop&#xE1;dn&#x11B; si ale babi&#x10D;ka nejsp&#xED;&#x161; zlomila kloub a Connell musel odv&#xE9;zt Lorraine do Sliga do nemocnice ." dictexample="1" use="other" commfuntype="decl" commfunsubtype="struktura&#x10D;n&#xED;" commfunnote="po vsuvce, tj. po topic shiftu" pred="cs:rooney-normalni_lidi:0:364:4:w2 cs:rooney-normalni_lidi:0:364:4:w6" comment="po odveden&#xED; my&#x161;lenek mluv&#x10D;&#xED;ho (vsuvka) se zase vrac&#xED; k p&#x159;edchoz&#xED;mu t&#xE9;matu, tj. topic shift" predlemma="se zlomit" predtag="P7--3---------- VpFS----R-AAP--" predverbtag="------ VDA3SR" modift=""/>
  <item id="ex-25325" cql="q-22" xml="atwood-muzeum_zkamenel" en="" cs="cs:atwood-muzeum_zkamenel:0:864:1:w17" cst="ka&#x17E;dop&#xE1;dn&#x11B;" cssent="V&#xED; , &#x17E;e se z&#xED;tra r&#xE1;no vr&#xE1;t&#xED; , v&#x10D;as na vydatn&#xFD; ned&#x11B;ln&#xED; ob&#x11B;d , &#x17E;e z&#xED;tra ka&#x17E;dop&#xE1;dn&#x11B; p&#x16F;jde v&#x161;echno jako v&#x17E;dycky , &#x17E;e bude st&#xE1;t v kuchyni a pod&#xE1;vat m&#xED;chan&#xE1; vaj&#xED;&#x10D;ka na toustu pro sebe , holky i Elizabeth , zavinutou do modr&#xE9;ho frot&#xE9; &#x17E;upanu , vlasy jenom zpola u&#x10D;esan&#xE9; ." use="certain" certainty="highmedium" commfuntype="decl" commfunsubtype="sebep&#x159;esv&#x11B;d&#x10D;ov&#xE1;n&#xED;" commfunnote="nerozum&#xED;m &#xFA;pln&#x11B; kontextu" scope="sent" pred="cs:atwood-muzeum_zkamenel:0:864:1:w18" tfpos="neutral" sentpos="other" modalpersp="clear" comment="divn&#xFD; p&#x159;eklad, nerozum&#xED;m, cht&#x11B;lo by to vid&#x11B;t origin&#xE1;l" predlemma="j&#xED;t" predtag="VB-S---3F-AAI--" predverbtag="VDA3SF" modift=""/>
  <item id="ex-25303" cql="q-22" xml="Amis-Stastny_Jim" en="" cs="cs:Amis-Stastny_Jim:0:1325:12:w3" cst="ka&#x17E;dop&#xE1;dn&#x11B;" cssent="Welch by ka&#x17E;dop&#xE1;dn&#x11B; z&#xE1;&#x159;il ." use="certain" certainty="full" commfuntype="decl" commfunsubtype="p&#x159;esv&#x11B;d&#x10D;en&#xED;" commfunnote="p&#x159;edstava mluv&#x10D;&#xED;ho, hodnocen&#xED;" scope="sent" pred="cs:Amis-Stastny_Jim:0:1325:12:w4 cs:Amis-Stastny_Jim:0:1325:12:w2" tfpos="neutral" sentpos="other" modalpersp="clear" comment="s kondicion&#xE1;lem, bez jak&#xE9;hokoli kontrastu p&#x159;ed t&#xED;m se zd&#xE1; jistotn&#xED;" predlemma="z&#xE1;&#x159;it b&#xFD;t" predtag="VpMS----R-AAI-- Vc----------I--" predverbtag="VCA3SP A-----" modift=""/>
  <item id="ex-25989" cql="q-22" xml="Popper-hledani" en="" cs="cs:Popper-hledani:0:270:8:w1" cst="ka&#x17E;dop&#xE1;dn&#x11B;" cssent="ka&#x17E;dop&#xE1;dn&#x11B; je v&#x17E;dy nebezpe&#x10D;n&#xE9; ji ignorovat . &quot;" use="other" commfuntype="decl" commfunsubtype="citace" commfunnote="meta&#xFA;rove&#x148;, kousky cit&#xE1;tu vynech&#xE1;ny" pred="cs:Popper-hledani:0:270:8:w2 cs:Popper-hledani:0:270:8:w4" comment="metau&#x17E;it&#xED;, vytr&#x17E;en&#xE9; z kontextu; lexik&#xE1;ln&#xED; negace" predlemma="b&#xFD;t bezpe&#x10D;n&#xFD;" predtag="VB-S---3P-AAI-- AANS1----1N----" predverbtag="VDA3SP ------" modift=""/>
  <item id="ex-26229" cql="q-22" xml="wilson-cim_hori_svet" en="" cs="cs:wilson-cim_hori_svet:0:593:4:w1" cst="Ka&#x17E;dop&#xE1;dn&#x11B;" cssent="Ka&#x17E;dop&#xE1;dn&#x11B; se zavd&#x11B;&#x10D;&#xED;&#x161; Nanicovi ." use="certain" certainty="full" certaintynote="v&#xED;c ne&#x17E; 100%" commfuntype="decl" commfunsubtype="p&#x159;esv&#x11B;d&#x10D;en&#xED;" commfunnote="trochu i konektivn&#xED;" scope="sent" pred="cs:wilson-cim_hori_svet:0:593:4:w3 cs:wilson-cim_hori_svet:0:593:4:w2" tfpos="neutral" sentpos="other" modalpersp="clear" predlemma="zavd&#x11B;&#x10D;it se" predtag="VB-S---2P-AAP-- P7--4----------" predverbtag="VDA2SF ------" modift=""/>
  <item id="ex-25746" cql="q-22" xml="hosseini-lovec_draku" en="" cs="cs:hosseini-lovec_draku:0:2595:12:w2" cst="Ka&#x17E;dop&#xE1;dn&#x11B;" cssent="&#x201E; Ka&#x17E;dop&#xE1;dn&#x11B; mi v dopise psal , &#x17E;e i tob&#x11B; se tenhle p&#x159;&#xED;b&#x11B;h l&#xED;b&#xED; nejv&#xED;c , a tak jsem si myslel , &#x17E;e bych ti z n&#x11B;j chv&#xED;li &#x10D;etl ." use="other" commfuntype="decl" commfunsubtype="konektivn&#xED;" commfunnote="navazov&#xE1;n&#xED;, shrnut&#xED;" pred="cs:hosseini-lovec_draku:0:2595:12:w3 cs:hosseini-lovec_draku:0:2595:12:w6" comment="nezn&#xED; jako jistotn&#xED; s minulost&#xED;, sp&#xED;&#x161; navazovac&#xED;" predlemma="j&#xE1; ps&#xE1;t" predtag="PH-S3--1------- VpMS----R-AAI--" predverbtag="------ VDA3SR" modift=""/>
  <item id="ex-25587" cql="q-22" xml="evans-pomezi" en="" cs="cs:evans-pomezi:0:1556:10:w1" cst="Ka&#x17E;dop&#xE1;dn&#x11B;" cssent="Ka&#x17E;dop&#xE1;dn&#x11B; ji p&#x159;ekvapilo , p&#x17E;e c&#xED;t&#xED; kou&#x159; a &#x17E;e se nad n&#xED; val&#xED; &#x161;tiplav&#xFD; d&#xFD;m ." use="other" commfuntype="decl" commfunsubtype="konektivn&#xED;" commfunnote="navazov&#xE1;n&#xED; s kontrastem" pred="cs:evans-pomezi:0:1556:10:w3" predlemma="p&#x159;ekvapit" predtag="VpNS----R-AAP--" predverbtag="VDA3SR" modift=""/>
  <item id="ex-25309" cql="q-22" xml="angellova-dvoji_zivot" en="" cs="cs:angellova-dvoji_zivot:0:42:1:w1" cst="Ka&#x17E;dop&#xE1;dn&#x11B;" cssent="Ka&#x17E;dop&#xE1;dn&#x11B; do konce semestru zb&#xFD;valy cel&#xE9; dva m&#x11B;s&#xED;ce , co&#x17E; byl d&#x16F;vod , pro&#x10D; jsem rychle pot&#x159;ebovala sehnat tak velkou hotovost ." use="certain" certainty="medium" commfuntype="decl" commfunsubtype="konaktivn&#xED;" commfunnote="navazovac&#xED;, n&#xE1;vrat k t&#xE9;matu po vsuvce" scope="sent" pred="cs:angellova-dvoji_zivot:0:42:1:w5" tfpos="neutral" sentpos="other" modalpersp="clear" predlemma="zb&#xFD;vat" predtag="VpIP----R-AAI--" predverbtag="VDA3PR" modift=""/>
  <item id="ex-25777" cql="q-22" xml="kahneman-mysleni" en="" cs="cs:kahneman-mysleni:0:644:3:w1" cst="Ka&#x17E;dop&#xE1;dn&#x11B;" cssent="Ka&#x17E;dop&#xE1;dn&#x11B; je dobr&#xE9; si tuto v&#x11B;c zapamatovat ." use="other" commfuntype="decl" commfunsubtype="vyvozen&#xED;, shrnut&#xED;" pred="cs:kahneman-mysleni:0:644:3:w2 cs:kahneman-mysleni:0:644:3:w3" predlemma="b&#xFD;t dobr&#xFD;" predtag="VB-S---3P-AAI-- AANS1----1A----" predverbtag="VDA3SP ------" modift=""/>
  <item id="ex-25508" cql="q-22" xml="Burns-Mlikar" en="" cs="cs:Burns-Mlikar:0:136:21:w1" cst="Ka&#x17E;dop&#xE1;dn&#x11B;" cssent="Ka&#x17E;dop&#xE1;dn&#x11B; chud&#xE1;k McN&#x11B;kdo ." use="other" commfuntype="expr" commfunsubtype="hodnocen&#xED;" commfunnote="soucit" comment="hodnocen&#xED;, exprese, asi siln&#x11B;j&#x161;&#xED; v konstrukci s elipsou slovesa" predlemma="" predtag="" predverbtag="" modift=""/>
  <item id="ex-26051" cql="q-22" xml="rowlingova-hpot_fenix" en="" cs="cs:rowlingova-hpot_fenix:0:5246:3:w2" cst="ka&#x17E;dop&#xE1;dn&#x11B;" cssent="Ale ka&#x17E;dop&#xE1;dn&#x11B; u&#x17E;ite&#x10D;n&#xE9; &#x2026; &quot;" use="other" commfuntype="decl" commfunsubtype="zd&#x16F;razn&#x11B;n&#xED;" commfunnote="zd&#x16F;razn&#x11B;n&#xED; n&#xE1;zoru (v kontrastu)" comment="kontrastov&#xE9; zd&#x16F;razn&#x11B;n&#xED;: &quot;divn&#xE9;, ale kazdop&#xE1;dn&#x11B; u&#x17E;ite&#x10D;n&#xE9;&quot;" predlemma="" predtag="" predverbtag="" modift=""/>
  <item id="ex-26236" cql="q-22" xml="woolfova-dallowayova" en="" cs="cs:woolfova-dallowayova:0:270:3:w1" cst="Ka&#x17E;dop&#xE1;dn&#x11B;" cssent="Ka&#x17E;dop&#xE1;dn&#x11B; prohl&#xE9;dla Hugha Whitbreada - toho &#xFA;&#x17E;asn&#xE9;ho Hugha - v dob&#x11B; , kdy mu Clarissa a v&#x161;ichni ostatn&#xED; le&#x17E;eli u nohou ." use="certain" certainty="full" certaintynote="opakov&#xE1;n&#xED; zesiluje, mo&#x17E;n&#xE1; na hranici s ur&#x10D;itou silnou v&#xFD;stabvou textu (konektivn&#xED; fce)" commfuntype="decl" commfunsubtype="argumentace" commfunnote="zd&#x16F;vodn&#x11B;n&#xED; n&#xE1;zoru" scope="sent" pred="cs:woolfova-dallowayova:0:270:3:w2" tfpos="neutral" sentpos="first" modalpersp="clear" modif="Ka&#x17E;dop&#xE1;dn&#x11B; se sna&#x17E;ila br&#xE1;t v&#x11B;ci za spr&#xE1;vn&#xFD; konec " comment="zes&#xED;len&#xED; v opakov&#xE1;n&#xED; &quot;ka&#x17E;dop&#xE1;dn&#x11B;&quot;" predlemma="prohl&#xE9;dnout" predtag="VpFS----R-AAP-1" predverbtag="VDA3SR" modift=""/>
  <item id="ex-25711" cql="q-22" xml="Grisham-Kral_advokatu" en="" cs="cs:Grisham-Kral_advokatu:0:249:4:w11" cst="ka&#x17E;dop&#xE1;dn&#x11B;" cssent="Bennett sice bezohledn&#x11B; ni&#x10D;iv&#xFD; styl p&#x159;edm&#x11B;stsk&#xE9; v&#xFD;stavby nevynalezl , ale ka&#x17E;dop&#xE1;dn&#x11B; ho zdokonalil ." use="other" commfuntype="decl" commfunsubtype="zd&#x16F;razn&#x11B;n&#xED;" commfunnote="v p&#x159;&#xED;pustce, zd&#x16F;razn&#x11B;n&#xED; &quot;ale&quot;" pred="cs:Grisham-Kral_advokatu:0:249:4:w13" comment="v p&#x159;&#xED;pustkov&#xE9; struktu&#x159;e" predlemma="zdokonalit" predtag="VpMS----R-AAP--" predverbtag="VDA3SR" modift=""/>
  <item id="ex-25509" cql="q-22" xml="Burns-Mlikar" en="" cs="cs:Burns-Mlikar:0:137:7:w5" cst="ka&#x17E;dop&#xE1;dn&#x11B;" cssent="Nahlas jsem o tom ka&#x17E;dop&#xE1;dn&#x11B; ne&#x159;ekla nic a on o tom taky nic ne&#x159;&#xED;kal , jako kdyby to byla norm&#xE1;lka , st&#xE1;t n&#x11B;kde , kde za letn&#xED;ho ve&#x10D;era ve t&#x159;i &#x10D;tvrt&#x11B; na deset je&#x161;t&#x11B; nikdy nikdo nest&#xE1;l , teda ur&#x10D;it&#x11B; ne vedle n&#xE1;ctilet&#xFD; holky , kter&#xE1; dr&#x17E;&#xED; u&#x159;&#xED;znutou hlavu , a bavit se s n&#xED; o tom , &#x17E;e kluk , se kter&#xFD;m m&#xE1; jako&#x17E;e vztah , nejsp&#xED;&#x161; p&#x159;ijde jeho p&#x159;i&#x10D;in&#x11B;n&#xED;m o &#x17E;ivot ." use="content" pred="cs:Burns-Mlikar:0:137:7:w6" comment="ve smyslu rozhodn&#x11B;? zd&#x16F;raz&#x148;ovac&#xED;" predlemma="&#x159;&#xED;ci" predtag="VpFS----R-NAP--" predverbtag="VDA1SR" modift=""/>
  <item id="ex-25620" cql="q-22" xml="Forsyth-Ctvrty_protoko" en="" cs="cs:Forsyth-Ctvrty_protoko:0:1862:3:w1" cst="Ka&#x17E;dop&#xE1;dn&#x11B;" cssent="Ka&#x17E;dop&#xE1;dn&#x11B; , tohle je to , na &#x10D;em pracuji od &#x10D;ervna 1983 &#x2026; &quot;" use="other" commfuntype="decl" commfunsubtype="konektivn&#xED;" commfunnote="shrnut&#xED; po v&#xFD;&#x10D;tu, trochu topic-shift" pred="cs:Forsyth-Ctvrty_protoko:0:1862:3:w4 cs:Forsyth-Ctvrty_protoko:0:1862:3:w5" comment="prototypick&#xE9; (meziv&#x11B;tn&#xE9;) konektivn&#xED; u&#x17E;it&#xED;, ale ne do slovn&#xED;ku, rad&#x161;i &#x10D;esk&#xFD; origin&#xE1;ln&#xED; p&#x159;&#xED;klad" predlemma="b&#xFD;t ten" predtag="VB-S---3P-AAI-- PDNS1----------" predverbtag="VDA3SP ------" modift=""/>
  <item id="ex-25910" cql="q-22" xml="mitchell-atlas_mraku" en="" cs="cs:mitchell-atlas_mraku:0:816:2:w7" cst="ka&#x17E;dop&#xE1;dn&#x11B;" cssent="&#x201E; Garcia se k tomu autu ka&#x17E;dop&#xE1;dn&#x11B; hod&#xED; ." use="content" pred="cs:mitchell-atlas_mraku:0:816:2:w8" comment="hranice mezi plnov&#xFD;znamov&#xFD;m a jin&#xFD;m (hodnocen&#xED;)" predlemma="hodit" predtag="VB-S---3P-AAI--" predverbtag="VDA3SP" modift=""/>
  <item id="ex-25677" cql="q-22" xml="Gaiman-Nikdykde" en="" cs="cs:Gaiman-Nikdykde:0:106:4:w4" cst="ka&#x17E;dop&#xE1;dn&#x11B;" cssent="Ale byl to ka&#x17E;dop&#xE1;dn&#x11B; nejd&#x16F;le&#x17E;it&#x11B;j&#x161;&#xED; den v jeho &#x17E;ivot&#x11B; ." use="other" commfuntype="decl" commfunsubtype="zd&#x16F;razn&#x11B;n&#xED;" commfunnote="opakov&#xE1;n&#xED; d&#x159;&#xED;ve vysloven&#xE9;ho s extra d&#x16F;razem (a po kontrastu)" pred="cs:Gaiman-Nikdykde:0:106:4:w2 cs:Gaiman-Nikdykde:0:106:4:w6" predlemma="b&#xFD;t den" predtag="VpIS----R-AAI-- NNIS1-----A----" predverbtag="VDA3SR ------" modift=""/>
</examples>
